[
  {
    "id": "PS11_P1_ELE_637",
    "topic": "Electricity (Electrostatics and Electric circuits)",
    "subtopic": "Electric Circuits",
    "paper": "paper1",
    "difficulty": "hard",
    "question": "A battery with an emf of 37 V and an internal resistance of 1.35 \u03a9 is connected to an external resistor of 28.00 \u03a9. Calculate the potential difference across the external resistor (terminal voltage).",
    "correct_answer": "35.29",
    "wrong_answers_pool": [
      "352.90",
      "45.29",
      "17.64",
      "3.53",
      "25.29",
      "70.58"
    ],
    "explanation": "I = emf / (R + r) = 37 / (28.00 + 1.35) = 1.260 A. V_load = I * R = 1.260 * 28.00 = 35.29 V.",
    "exam_id": "EXAM_2026-W26_grade11_physical_sciences_paper1_1"
  },
  {
    "id": "PS11_P1_NEW_052",
    "topic": "Newton\u2019s Laws and Forces",
    "subtopic": "Newton's Second Law",
    "paper": "paper1",
    "difficulty": "hard",
    "question": "A 79 kg block is pulled along a rough horizontal surface by a force of 999 N at an angle of 32\u00b0 above the horizontal. If the kinetic friction is 60 N, calculate the acceleration of the block.",
    "correct_answer": "9.96",
    "wrong_answers_pool": [
      "19.92",
      "99.20",
      "1.00",
      "99.60",
      "19.96",
      "4.98"
    ],
    "explanation": "Fx = F_applied * cos(\u03b8) = 999 * cos(32\u00b0) = 847.20 N. F_net = Fx - fk = 847.20 - 60 = 787.20 N. a = F_net / m = 787.20 / 79 = 9.96 m/s\u00b2.",
    "exam_id": "EXAM_2026-W26_grade11_physical_sciences_paper1_2"
  },
  {
    "id": "PS11_P1_WAV_641",
    "topic": "Waves, Sound and Light",
    "subtopic": "Critical angle and total internal reflection",
    "paper": "paper1",
    "difficulty": "hard",
    "question": "Calculate the critical angle for light passing from a medium with refractive index 1.62 into a medium with refractive index 1.21.",
    "correct_answer": "48.3\u00b0",
    "wrong_answers_pool": [
      "96.60",
      "24.15",
      "38.30",
      "4.83",
      "483.00",
      "58.30"
    ],
    "explanation": "sin(\u03b8_c) = n2 / n1 = 1.21 / 1.62. \u03b8_c = arcsin(1.21 / 1.62) = 48.3\u00b0.",
    "exam_id": "EXAM_2026-W26_grade11_physical_sciences_paper1_3"
  },
  {
    "id": "PS11_P1_MAG_076",
    "topic": "Magnetism and Electromagnetism",
    "subtopic": "Faraday's Law of Electromagnetic Induction",
    "paper": "paper1",
    "difficulty": "hard",
    "question": "A circular coil of 506 turns and radius 0.44 m is placed in a magnetic field perpendicular to its plane. The magnetic field increases from 0.43 T to 1.50 T in 1.14 s. Calculate the induced emf.",
    "correct_answer": "294.01",
    "wrong_answers_pool": [
      "2940.10",
      "284.01",
      "147.00",
      "588.02",
      "304.01",
      "29.40"
    ],
    "explanation": "A = \u03c0r\u00b2 = \u03c0(0.44)\u00b2 = 0.6180 m\u00b2. \u0394\u03a6 = (B_f - B_i) * A = (1.50 - 0.43) * 0.6180. emf = N(\u0394\u03a6/\u0394t) = 506 * \u0394\u03a6 / 1.14 = 294.01 V.",
    "exam_id": "EXAM_2026-W26_grade11_physical_sciences_paper1_4"
  },
  {
    "id": "PS11_P1_NEW_483",
    "topic": "Newton\u2019s Laws and Forces",
    "subtopic": "Newton's Second Law",
    "paper": "paper1",
    "difficulty": "hard",
    "question": "A 29 kg block is pulled along a rough horizontal surface by a force of 558 N at an angle of 16\u00b0 above the horizontal. If the kinetic friction is 23 N, calculate the acceleration of the block.",
    "correct_answer": "17.70",
    "wrong_answers_pool": [
      "27.70",
      "177.00",
      "8.85",
      "35.40",
      "1.77",
      "7.70"
    ],
    "explanation": "Fx = F_applied * cos(\u03b8) = 558 * cos(16\u00b0) = 536.38 N. F_net = Fx - fk = 536.38 - 23 = 513.38 N. a = F_net / m = 513.38 / 29 = 17.70 m/s\u00b2.",
    "exam_id": "EXAM_2026-W26_grade11_physical_sciences_paper1_5"
  },
  {
    "id": "PS11_P1_MAG_027",
    "topic": "Magnetism and Electromagnetism",
    "subtopic": "Faraday's Law of Electromagnetic Induction",
    "paper": "paper1",
    "difficulty": "medium",
    "question": "A uniform magnetic field of 0.73 T passes perpendicular to a loop of area 270 cm\u00b2. Calculate the magnetic flux passing through the loop.",
    "correct_answer": "1.97x10^-02",
    "wrong_answers_pool": [
      "1.68x10^-04",
      "1.97x10^-01",
      "2.20x10^-03",
      "2.31x10^-01",
      "2.04x10^-01",
      "2.23x10^00"
    ],
    "explanation": "\u03a6 = B * A * cos(0\u00b0) = 0.73 * 0.0270 * 1 = 1.97x10^-02 Wb.",
    "exam_id": "EXAM_2026-W26_grade11_physical_sciences_paper1_6"
  },
  {
    "id": "PS11_P1_WAV_865",
    "topic": "Waves, Sound and Light",
    "subtopic": "Critical angle and total internal reflection",
    "paper": "paper1",
    "difficulty": "hard",
    "question": "Calculate the critical angle for light passing from a medium with refractive index 2.16 into a medium with refractive index 1.80.",
    "correct_answer": "56.4\u00b0",
    "wrong_answers_pool": [
      "46.40",
      "28.20",
      "112.80",
      "66.40",
      "5.64",
      "564.00"
    ],
    "explanation": "sin(\u03b8_c) = n2 / n1 = 1.80 / 2.16. \u03b8_c = arcsin(1.80 / 2.16) = 56.4\u00b0.",
    "exam_id": "EXAM_2026-W26_grade11_physical_sciences_paper1_7"
  },
  {
    "id": "PS11_P1_ELE_335",
    "topic": "Electricity (Electrostatics and Electric circuits)",
    "subtopic": "Electric Circuits",
    "paper": "paper1",
    "difficulty": "hard",
    "question": "A battery with an emf of 24 V and an internal resistance of 0.81 \u03a9 is connected to an external resistor of 26.12 \u03a9. Calculate the potential difference across the external resistor (terminal voltage).",
    "correct_answer": "23.28",
    "wrong_answers_pool": [
      "33.28",
      "232.80",
      "11.64",
      "46.56",
      "13.28",
      "2.33"
    ],
    "explanation": "I = emf / (R + r) = 24 / (26.12 + 0.81) = 0.891 A. V_load = I * R = 0.891 * 26.12 = 23.28 V.",
    "exam_id": "EXAM_2026-W26_grade11_physical_sciences_paper1_8"
  },
  {
    "id": "PS11_P1_NEW_097",
    "topic": "Newton\u2019s Laws and Forces",
    "subtopic": "Newton's Law of Universal Gravitation",
    "paper": "paper1",
    "difficulty": "medium",
    "question": "Calculate the gravitational force of attraction between two masses, 647 kg and 695 kg, separated by a distance of 22 m. (G = 6.67x10^-11 N\u00b7m\u00b2/kg\u00b2)",
    "correct_answer": "6.20x10^-08",
    "wrong_answers_pool": [
      "7.41x10^-07",
      "7.39x10^-09",
      "5.15x10^-09",
      "1.25x10^-07",
      "1.10x10^-07",
      "3.31x10^-08"
    ],
    "explanation": "F = G * m1 * m2 / r\u00b2 = (6.67x10^-11) * 647 * 695 / 22\u00b2 = 6.20x10^-08 N.",
    "exam_id": "EXAM_2026-W26_grade11_physical_sciences_paper1_9"
  },
  {
    "id": "PS11_P1_NEW_558",
    "topic": "Newton\u2019s Laws and Forces",
    "subtopic": "Newton's Second Law",
    "paper": "paper1",
    "difficulty": "hard",
    "question": "A 37 kg block is pulled along a rough horizontal surface by a force of 528 N at an angle of 53\u00b0 above the horizontal. If the kinetic friction is 34 N, calculate the acceleration of the block.",
    "correct_answer": "7.67",
    "wrong_answers_pool": [
      "3.83",
      "58.83",
      "15.34",
      "76.70",
      "0.77",
      "17.67"
    ],
    "explanation": "Fx = F_applied * cos(\u03b8) = 528 * cos(53\u00b0) = 317.76 N. F_net = Fx - fk = 317.76 - 34 = 283.76 N. a = F_net / m = 283.76 / 37 = 7.67 m/s\u00b2.",
    "exam_id": "EXAM_2026-W26_grade11_physical_sciences_paper1_10"
  },
  {
    "id": "PS11_P1_MAG_311",
    "topic": "Magnetism and Electromagnetism",
    "subtopic": "Faraday's Law of Electromagnetic Induction",
    "paper": "paper1",
    "difficulty": "hard",
    "question": "A circular coil of 334 turns and radius 0.40 m is placed in a magnetic field perpendicular to its plane. The magnetic field increases from 0.76 T to 1.82 T in 0.49 s. Calculate the induced emf.",
    "correct_answer": "359.09",
    "wrong_answers_pool": [
      "3590.90",
      "369.09",
      "35.91",
      "718.18",
      "179.54",
      "349.09"
    ],
    "explanation": "A = \u03c0r\u00b2 = \u03c0(0.40)\u00b2 = 0.4951 m\u00b2. \u0394\u03a6 = (B_f - B_i) * A = (1.82 - 0.76) * 0.4951. emf = N(\u0394\u03a6/\u0394t) = 334 * \u0394\u03a6 / 0.49 = 359.09 V.",
    "exam_id": "EXAM_2026-W26_grade11_physical_sciences_paper1_11"
  },
  {
    "id": "PS11_P1_ELE_562",
    "topic": "Electricity (Electrostatics and Electric circuits)",
    "subtopic": "Electric Circuits",
    "paper": "paper1",
    "difficulty": "hard",
    "question": "A battery with an emf of 46 V and an internal resistance of 1.80 \u03a9 is connected to an external resistor of 24.95 \u03a9. Calculate the potential difference across the external resistor (terminal voltage).",
    "correct_answer": "42.91",
    "wrong_answers_pool": [
      "52.91",
      "32.91",
      "429.10",
      "4.29",
      "21.45",
      "85.82"
    ],
    "explanation": "I = emf / (R + r) = 46 / (24.95 + 1.80) = 1.720 A. V_load = I * R = 1.720 * 24.95 = 42.91 V.",
    "exam_id": "EXAM_2026-W26_grade11_physical_sciences_paper1_12"
  },
  {
    "id": "PS11_P1_MAG_820",
    "topic": "Magnetism and Electromagnetism",
    "subtopic": "Faraday's Law of Electromagnetic Induction",
    "paper": "paper1",
    "difficulty": "medium",
    "question": "A uniform magnetic field of 3.57 T passes perpendicular to a loop of area 220 cm\u00b2. Calculate the magnetic flux passing through the loop.",
    "correct_answer": "7.86x10^-02",
    "wrong_answers_pool": [
      "9.11x10^-03",
      "8.23x10^-04",
      "7.94x10^00",
      "6.31x10^-03",
      "8.05x10^00",
      "7.76x10^-01"
    ],
    "explanation": "\u03a6 = B * A * cos(0\u00b0) = 3.57 * 0.0220 * 1 = 7.86x10^-02 Wb.",
    "exam_id": "EXAM_2026-W26_grade11_physical_sciences_paper1_13"
  },
  {
    "id": "PS11_P1_WAV_054",
    "topic": "Waves, Sound and Light",
    "subtopic": "Snell's Law",
    "paper": "paper1",
    "difficulty": "medium",
    "question": "Light travels from a medium with refractive index 1.63 into a medium with refractive index 1.81. If the angle of incidence is 17\u00b0, calculate the angle of refraction.",
    "correct_answer": "15.3\u00b0",
    "wrong_answers_pool": [
      "30.60",
      "1.53",
      "25.30",
      "5.30",
      "153.00",
      "7.65"
    ],
    "explanation": "n1 * sin(\u03b81) = n2 * sin(\u03b82) => 1.63 * sin(17\u00b0) = 1.81 * sin(\u03b82) => \u03b82 = arcsin((1.63 * sin(17\u00b0)) / 1.81) = 15.3\u00b0.",
    "exam_id": "EXAM_2026-W26_grade11_physical_sciences_paper1_14"
  },
  {
    "id": "PS11_P1_VEC_362",
    "topic": "Vectors and Scalars",
    "subtopic": "Addition of vectors",
    "paper": "paper1",
    "difficulty": "hard",
    "question": "Two forces act on an object: F1 = 28 N at 31\u00b0 and F2 = 94 N at 107\u00b0 (angles measured counterclockwise from positive x-axis). What is the magnitude of the resultant force?",
    "correct_answer": "104.37 N",
    "wrong_answers_pool": [
      "94.37",
      "1043.70",
      "208.74",
      "52.19",
      "114.37",
      "10.44"
    ],
    "explanation": "Rx = 28cos(31) + 94cos(107) = -3.48 N. Ry = 28sin(31) + 94sin(107) = 104.31 N. Resultant = \u221a(-3.48\u00b2 + 104.31\u00b2) = 104.37 N.",
    "exam_id": "EXAM_2026-W26_grade11_physical_sciences_paper1_15"
  },
  {
    "id": "PS11_P1_NEW_658",
    "topic": "Newton\u2019s Laws and Forces",
    "subtopic": "Newton's Second Law",
    "paper": "paper1",
    "difficulty": "hard",
    "question": "A 17 kg block is pulled along a rough horizontal surface by a force of 508 N at an angle of 51\u00b0 above the horizontal. If the kinetic friction is 86 N, calculate the acceleration of the block.",
    "correct_answer": "13.75",
    "wrong_answers_pool": [
      "27.50",
      "3.75",
      "23.75",
      "1.38",
      "137.50",
      "6.88"
    ],
    "explanation": "Fx = F_applied * cos(\u03b8) = 508 * cos(51\u00b0) = 319.69 N. F_net = Fx - fk = 319.69 - 86 = 233.69 N. a = F_net / m = 233.69 / 17 = 13.75 m/s\u00b2.",
    "exam_id": "EXAM_2026-W26_grade11_physical_sciences_paper1_16"
  },
  {
    "id": "PS11_P1_MAG_519",
    "topic": "Magnetism and Electromagnetism",
    "subtopic": "Faraday's Law of Electromagnetic Induction",
    "paper": "paper1",
    "difficulty": "medium",
    "question": "A uniform magnetic field of 2.75 T passes perpendicular to a loop of area 17 cm\u00b2. Calculate the magnetic flux passing through the loop.",
    "correct_answer": "4.68x10^-03",
    "wrong_answers_pool": [
      "5.21x10^-04",
      "4.20x10^-05",
      "4.29x10^-05",
      "5.07x10^-05",
      "5.01x10^-01",
      "4.02x10^-04"
    ],
    "explanation": "\u03a6 = B * A * cos(0\u00b0) = 2.75 * 0.0017 * 1 = 4.68x10^-03 Wb.",
    "exam_id": "EXAM_2026-W26_grade11_physical_sciences_paper1_17"
  },
  {
    "id": "PS11_P1_ELE_550",
    "topic": "Electricity (Electrostatics and Electric circuits)",
    "subtopic": "Electric Circuits",
    "paper": "paper1",
    "difficulty": "hard",
    "question": "A battery with an emf of 46 V and an internal resistance of 2.61 \u03a9 is connected to an external resistor of 26.19 \u03a9. Calculate the potential difference across the external resistor (terminal voltage).",
    "correct_answer": "41.83",
    "wrong_answers_pool": [
      "31.83",
      "83.66",
      "418.30",
      "20.91",
      "4.18",
      "51.83"
    ],
    "explanation": "I = emf / (R + r) = 46 / (26.19 + 2.61) = 1.597 A. V_load = I * R = 1.597 * 26.19 = 41.83 V.",
    "exam_id": "EXAM_2026-W26_grade11_physical_sciences_paper1_18"
  },
  {
    "id": "PS11_P1_WAV_084",
    "topic": "Waves, Sound and Light",
    "subtopic": "Snell's Law",
    "paper": "paper1",
    "difficulty": "medium",
    "question": "Light travels from a medium with refractive index 1.09 into a medium with refractive index 1.91. If the angle of incidence is 34\u00b0, calculate the angle of refraction.",
    "correct_answer": "18.6\u00b0",
    "wrong_answers_pool": [
      "1.86",
      "186.00",
      "28.60",
      "9.30",
      "8.60",
      "37.20"
    ],
    "explanation": "n1 * sin(\u03b81) = n2 * sin(\u03b82) => 1.09 * sin(34\u00b0) = 1.91 * sin(\u03b82) => \u03b82 = arcsin((1.09 * sin(34\u00b0)) / 1.91) = 18.6\u00b0.",
    "exam_id": "EXAM_2026-W26_grade11_physical_sciences_paper1_19"
  },
  {
    "id": "PS11_P1_WAV_830",
    "topic": "Waves, Sound and Light",
    "subtopic": "Critical angle and total internal reflection",
    "paper": "paper1",
    "difficulty": "hard",
    "question": "Calculate the critical angle for light passing from a medium with refractive index 1.58 into a medium with refractive index 1.19.",
    "correct_answer": "48.6\u00b0",
    "wrong_answers_pool": [
      "4.86",
      "38.60",
      "486.00",
      "97.20",
      "58.60",
      "24.30"
    ],
    "explanation": "sin(\u03b8_c) = n2 / n1 = 1.19 / 1.58. \u03b8_c = arcsin(1.19 / 1.58) = 48.6\u00b0.",
    "exam_id": "EXAM_2026-W26_grade11_physical_sciences_paper1_20"
  },
  {
    "id": "PS11_P1_NEW_689",
    "topic": "Newton\u2019s Laws and Forces",
    "subtopic": "Newton's Law of Universal Gravitation",
    "paper": "paper1",
    "difficulty": "medium",
    "question": "Calculate the gravitational force of attraction between two masses, 756 kg and 724 kg, separated by a distance of 4 m. (G = 6.67x10^-11 N\u00b7m\u00b2/kg\u00b2)",
    "correct_answer": "2.28x10^-06",
    "wrong_answers_pool": [
      "2.51x10^-07",
      "1.95x10^-07",
      "2.27x10^-05",
      "2.46x10^-07",
      "2.45x10^-05",
      "4.49x10^-06"
    ],
    "explanation": "F = G * m1 * m2 / r\u00b2 = (6.67x10^-11) * 756 * 724 / 4\u00b2 = 2.28x10^-06 N.",
    "exam_id": "EXAM_2026-W26_grade11_physical_sciences_paper1_21"
  },
  {
    "id": "PS11_P1_MAG_039",
    "topic": "Magnetism and Electromagnetism",
    "subtopic": "Faraday's Law of Electromagnetic Induction",
    "paper": "paper1",
    "difficulty": "medium",
    "question": "A uniform magnetic field of 3.74 T passes perpendicular to a loop of area 192 cm\u00b2. Calculate the magnetic flux passing through the loop.",
    "correct_answer": "7.18x10^-02",
    "wrong_answers_pool": [
      "6.90x10^-03",
      "7.10x10^-01",
      "7.32x10^-04",
      "6.21x10^-03",
      "6.41x10^-03",
      "8.27x10^-03"
    ],
    "explanation": "\u03a6 = B * A * cos(0\u00b0) = 3.74 * 0.0192 * 1 = 7.18x10^-02 Wb.",
    "exam_id": "EXAM_2026-W26_grade11_physical_sciences_paper1_22"
  },
  {
    "id": "PS11_P1_MAG_996",
    "topic": "Magnetism and Electromagnetism",
    "subtopic": "Faraday's Law of Electromagnetic Induction",
    "paper": "paper1",
    "difficulty": "hard",
    "question": "A circular coil of 386 turns and radius 0.09 m is placed in a magnetic field perpendicular to its plane. The magnetic field increases from 0.12 T to 1.70 T in 0.22 s. Calculate the induced emf.",
    "correct_answer": "75.34",
    "wrong_answers_pool": [
      "150.68",
      "753.40",
      "65.34",
      "7.53",
      "37.67",
      "85.34"
    ],
    "explanation": "A = \u03c0r\u00b2 = \u03c0(0.09)\u00b2 = 0.0276 m\u00b2. \u0394\u03a6 = (B_f - B_i) * A = (1.70 - 0.12) * 0.0276. emf = N(\u0394\u03a6/\u0394t) = 386 * \u0394\u03a6 / 0.22 = 75.34 V.",
    "exam_id": "EXAM_2026-W26_grade11_physical_sciences_paper1_23"
  },
  {
    "id": "PS11_P1_WAV_223",
    "topic": "Waves, Sound and Light",
    "subtopic": "Snell's Law",
    "paper": "paper1",
    "difficulty": "medium",
    "question": "Light travels from a medium with refractive index 1.28 into a medium with refractive index 1.81. If the angle of incidence is 33\u00b0, calculate the angle of refraction.",
    "correct_answer": "22.7\u00b0",
    "wrong_answers_pool": [
      "45.40",
      "227.00",
      "12.70",
      "2.27",
      "11.35",
      "32.70"
    ],
    "explanation": "n1 * sin(\u03b81) = n2 * sin(\u03b82) => 1.28 * sin(33\u00b0) = 1.81 * sin(\u03b82) => \u03b82 = arcsin((1.28 * sin(33\u00b0)) / 1.81) = 22.7\u00b0.",
    "exam_id": "EXAM_2026-W26_grade11_physical_sciences_paper1_24"
  },
  {
    "id": "PS11_P1_NEW_349",
    "topic": "Newton\u2019s Laws and Forces",
    "subtopic": "Newton's Second Law",
    "paper": "paper1",
    "difficulty": "hard",
    "question": "A 63 kg block is pulled along a rough horizontal surface by a force of 221 N at an angle of 58\u00b0 above the horizontal. If the kinetic friction is 73 N, calculate the acceleration of the block.",
    "correct_answer": "0.70",
    "wrong_answers_pool": [
      "0.35",
      "10.70",
      "0.07",
      "0.49",
      "7.00",
      "1.40"
    ],
    "explanation": "Fx = F_applied * cos(\u03b8) = 221 * cos(58\u00b0) = 117.11 N. F_net = Fx - fk = 117.11 - 73 = 44.11 N. a = F_net / m = 44.11 / 63 = 0.70 m/s\u00b2.",
    "exam_id": "EXAM_2026-W26_grade11_physical_sciences_paper1_25"
  },
  {
    "id": "PS11_P1_VEC_492",
    "topic": "Vectors and Scalars",
    "subtopic": "Addition of vectors",
    "paper": "paper1",
    "difficulty": "hard",
    "question": "Two forces act on an object: F1 = 51 N at 16\u00b0 and F2 = 40 N at 132\u00b0 (angles measured counterclockwise from positive x-axis). What is the magnitude of the resultant force?",
    "correct_answer": "49.12 N",
    "wrong_answers_pool": [
      "24.56",
      "491.20",
      "4.91",
      "98.24",
      "39.12",
      "59.12"
    ],
    "explanation": "Rx = 51cos(16) + 40cos(132) = 22.26 N. Ry = 51sin(16) + 40sin(132) = 43.78 N. Resultant = \u221a(22.26\u00b2 + 43.78\u00b2) = 49.12 N.",
    "exam_id": "EXAM_2026-W26_grade11_physical_sciences_paper1_26"
  },
  {
    "id": "PS11_P1_MAG_098",
    "topic": "Magnetism and Electromagnetism",
    "subtopic": "Faraday's Law of Electromagnetic Induction",
    "paper": "paper1",
    "difficulty": "medium",
    "question": "A uniform magnetic field of 3.81 T passes perpendicular to a loop of area 72 cm\u00b2. Calculate the magnetic flux passing through the loop.",
    "correct_answer": "2.74x10^-02",
    "wrong_answers_pool": [
      "3.22x10^00",
      "2.54x10^-03",
      "2.63x10^00",
      "2.49x10^-01",
      "3.04x10^-03",
      "2.25x10^-03"
    ],
    "explanation": "\u03a6 = B * A * cos(0\u00b0) = 3.81 * 0.0072 * 1 = 2.74x10^-02 Wb.",
    "exam_id": "EXAM_2026-W26_grade11_physical_sciences_paper1_27"
  },
  {
    "id": "PS11_P1_NEW_451",
    "topic": "Newton\u2019s Laws and Forces",
    "subtopic": "Newton's Law of Universal Gravitation",
    "paper": "paper1",
    "difficulty": "medium",
    "question": "Calculate the gravitational force of attraction between two masses, 650 kg and 198 kg, separated by a distance of 18 m. (G = 6.67x10^-11 N\u00b7m\u00b2/kg\u00b2)",
    "correct_answer": "2.65x10^-08",
    "wrong_answers_pool": [
      "2.73x10^-07",
      "1.45x10^-08",
      "2.63x10^-07",
      "2.60x10^-07",
      "3.09x10^-09",
      "1.26x10^-08"
    ],
    "explanation": "F = G * m1 * m2 / r\u00b2 = (6.67x10^-11) * 650 * 198 / 18\u00b2 = 2.65x10^-08 N.",
    "exam_id": "EXAM_2026-W26_grade11_physical_sciences_paper1_28"
  },
  {
    "id": "PS11_P1_ELE_738",
    "topic": "Electricity (Electrostatics and Electric circuits)",
    "subtopic": "Electric Circuits",
    "paper": "paper1",
    "difficulty": "hard",
    "question": "A battery with an emf of 34 V and an internal resistance of 1.32 \u03a9 is connected to an external resistor of 16.66 \u03a9. Calculate the potential difference across the external resistor (terminal voltage).",
    "correct_answer": "31.50",
    "wrong_answers_pool": [
      "15.75",
      "315.00",
      "3.15",
      "41.50",
      "63.00",
      "21.50"
    ],
    "explanation": "I = emf / (R + r) = 34 / (16.66 + 1.32) = 1.891 A. V_load = I * R = 1.891 * 16.66 = 31.50 V.",
    "exam_id": "EXAM_2026-W26_grade11_physical_sciences_paper1_29"
  },
  {
    "id": "PS11_P1_VEC_416",
    "topic": "Vectors and Scalars",
    "subtopic": "Resolution of vectors into components",
    "paper": "paper1",
    "difficulty": "medium",
    "question": "A force of 39 N acts at an angle of 55\u00b0 above the horizontal. Calculate its horizontal (Fx) and vertical (Fy) components.",
    "correct_answer": "Fx = 22.37 N, Fy = 31.95 N",
    "wrong_answers_pool": [
      "Fx = 31.95 N, Fy = 22.37 N",
      "Fx = 18.24 N, Fy = 32.48 N",
      "Fx = 23.20 N, Fy = 34.98 N",
      "Fx = 20.81 N, Fy = 37.72 N",
      "Fx = 18.27 N, Fy = 36.67 N",
      "Fx = 23.90 N, Fy = 29.52 N",
      "Fx = 21.83 N, Fy = 32.30 N",
      "Fx = 21.22 N, Fy = 25.83 N"
    ],
    "explanation": "Fx = F cos(\u03b8) = 39 cos(55\u00b0) = 22.37 N. Fy = F sin(\u03b8) = 39 sin(55\u00b0) = 31.95 N.",
    "exam_id": "EXAM_2026-W26_grade11_physical_sciences_paper1_30"
  },
  {
    "id": "PS11_P1_NEW_379",
    "topic": "Newton\u2019s Laws and Forces",
    "subtopic": "Newton's Second Law",
    "paper": "paper1",
    "difficulty": "hard",
    "question": "A 83 kg block is pulled along a rough horizontal surface by a force of 364 N at an angle of 54\u00b0 above the horizontal. If the kinetic friction is 11 N, calculate the acceleration of the block.",
    "correct_answer": "2.45",
    "wrong_answers_pool": [
      "6.00",
      "1.23",
      "24.50",
      "12.45",
      "4.90",
      "0.25"
    ],
    "explanation": "Fx = F_applied * cos(\u03b8) = 364 * cos(54\u00b0) = 213.95 N. F_net = Fx - fk = 213.95 - 11 = 202.95 N. a = F_net / m = 202.95 / 83 = 2.45 m/s\u00b2.",
    "exam_id": "EXAM_2026-W26_grade11_physical_sciences_paper1_31"
  },
  {
    "id": "PS11_P1_MAG_092",
    "topic": "Magnetism and Electromagnetism",
    "subtopic": "Faraday's Law of Electromagnetic Induction",
    "paper": "paper1",
    "difficulty": "medium",
    "question": "A uniform magnetic field of 2.53 T passes perpendicular to a loop of area 318 cm\u00b2. Calculate the magnetic flux passing through the loop.",
    "correct_answer": "8.06x10^-02",
    "wrong_answers_pool": [
      "9.43x10^-04",
      "9.05x10^-01",
      "9.00x10^-01",
      "9.41x10^-03",
      "7.51x10^-04",
      "6.86x10^-01"
    ],
    "explanation": "\u03a6 = B * A * cos(0\u00b0) = 2.53 * 0.0318 * 1 = 8.06x10^-02 Wb.",
    "exam_id": "EXAM_2026-W26_grade11_physical_sciences_paper1_32"
  },
  {
    "id": "PS11_P1_MAG_945",
    "topic": "Magnetism and Electromagnetism",
    "subtopic": "Faraday's Law of Electromagnetic Induction",
    "paper": "paper1",
    "difficulty": "medium",
    "question": "A uniform magnetic field of 3.22 T passes perpendicular to a loop of area 480 cm\u00b2. Calculate the magnetic flux passing through the loop.",
    "correct_answer": "1.55x10^-01",
    "wrong_answers_pool": [
      "1.44x10^00",
      "1.52x10^01",
      "1.60x10^-02",
      "1.48x10^-02",
      "1.79x10^01",
      "1.30x10^01"
    ],
    "explanation": "\u03a6 = B * A * cos(0\u00b0) = 3.22 * 0.0480 * 1 = 1.55x10^-01 Wb.",
    "exam_id": "EXAM_2026-W26_grade11_physical_sciences_paper1_33"
  },
  {
    "id": "PS11_P1_VEC_500",
    "topic": "Vectors and Scalars",
    "subtopic": "Resolution of vectors into components",
    "paper": "paper1",
    "difficulty": "medium",
    "question": "A force of 107 N acts at an angle of 42\u00b0 above the horizontal. Calculate its horizontal (Fx) and vertical (Fy) components.",
    "correct_answer": "Fx = 79.52 N, Fy = 71.60 N",
    "wrong_answers_pool": [
      "Fx = 71.60 N, Fy = 79.52 N",
      "Fx = 93.25 N, Fy = 65.62 N",
      "Fx = 64.21 N, Fy = 69.00 N",
      "Fx = 68.21 N, Fy = 63.84 N",
      "Fx = 67.36 N, Fy = 64.47 N",
      "Fx = 67.10 N, Fy = 65.64 N",
      "Fx = 65.63 N, Fy = 71.20 N",
      "Fx = 71.95 N, Fy = 72.24 N"
    ],
    "explanation": "Fx = F cos(\u03b8) = 107 cos(42\u00b0) = 79.52 N. Fy = F sin(\u03b8) = 107 sin(42\u00b0) = 71.60 N.",
    "exam_id": "EXAM_2026-W26_grade11_physical_sciences_paper1_34"
  },
  {
    "id": "PS11_P1_MAG_999",
    "topic": "Magnetism and Electromagnetism",
    "subtopic": "Faraday's Law of Electromagnetic Induction",
    "paper": "paper1",
    "difficulty": "hard",
    "question": "A circular coil of 572 turns and radius 0.23 m is placed in a magnetic field perpendicular to its plane. The magnetic field increases from 0.53 T to 3.93 T in 0.31 s. Calculate the induced emf.",
    "correct_answer": "1049.76",
    "wrong_answers_pool": [
      "104.98",
      "1039.76",
      "524.88",
      "1059.76",
      "2099.52",
      "10497.60"
    ],
    "explanation": "A = \u03c0r\u00b2 = \u03c0(0.23)\u00b2 = 0.1697 m\u00b2. \u0394\u03a6 = (B_f - B_i) * A = (3.93 - 0.53) * 0.1697. emf = N(\u0394\u03a6/\u0394t) = 572 * \u0394\u03a6 / 0.31 = 1049.76 V.",
    "exam_id": "EXAM_2026-W26_grade11_physical_sciences_paper1_35"
  },
  {
    "id": "PS11_P1_WAV_916",
    "topic": "Waves, Sound and Light",
    "subtopic": "Critical angle and total internal reflection",
    "paper": "paper1",
    "difficulty": "hard",
    "question": "Calculate the critical angle for light passing from a medium with refractive index 1.82 into a medium with refractive index 1.57.",
    "correct_answer": "59.7\u00b0",
    "wrong_answers_pool": [
      "29.85",
      "5.97",
      "119.40",
      "69.70",
      "597.00",
      "49.70"
    ],
    "explanation": "sin(\u03b8_c) = n2 / n1 = 1.57 / 1.82. \u03b8_c = arcsin(1.57 / 1.82) = 59.7\u00b0.",
    "exam_id": "EXAM_2026-W26_grade11_physical_sciences_paper1_36"
  },
  {
    "id": "PS11_P1_NEW_922",
    "topic": "Newton\u2019s Laws and Forces",
    "subtopic": "Newton's Law of Universal Gravitation",
    "paper": "paper1",
    "difficulty": "medium",
    "question": "Calculate the gravitational force of attraction between two masses, 335 kg and 682 kg, separated by a distance of 29 m. (G = 6.67x10^-11 N\u00b7m\u00b2/kg\u00b2)",
    "correct_answer": "1.81x10^-08",
    "wrong_answers_pool": [
      "3.15x10^-08",
      "2.91x10^-08",
      "2.05x10^-09",
      "1.92x10^-07",
      "1.81x10^-07",
      "1.89x10^-07"
    ],
    "explanation": "F = G * m1 * m2 / r\u00b2 = (6.67x10^-11) * 335 * 682 / 29\u00b2 = 1.81x10^-08 N.",
    "exam_id": "EXAM_2026-W26_grade11_physical_sciences_paper1_37"
  },
  {
    "id": "PS11_P1_ELE_095",
    "topic": "Electricity (Electrostatics and Electric circuits)",
    "subtopic": "Coulomb's Law",
    "paper": "paper1",
    "difficulty": "medium",
    "question": "Two point charges of 11.0 \u03bcC and 16.0 \u03bcC are separated by a distance of 91.0 cm. Calculate the electrostatic force between them. (k = 9x10^9 N\u00b7m\u00b2/C\u00b2)",
    "correct_answer": "1.91",
    "wrong_answers_pool": [
      "0.19",
      "3.65",
      "3.82",
      "19.10",
      "0.95",
      "11.91"
    ],
    "explanation": "F = k * q1 * q2 / r\u00b2 = (9x10^9) * (1.1e-05) * (1.6e-05) / (0.91\u00b2) = 1.91 N.",
    "exam_id": "EXAM_2026-W26_grade11_physical_sciences_paper1_38"
  },
  {
    "id": "PS11_P1_VEC_773",
    "topic": "Vectors and Scalars",
    "subtopic": "Resolution of vectors into components",
    "paper": "paper1",
    "difficulty": "medium",
    "question": "A force of 39 N acts at an angle of 35\u00b0 above the horizontal. Calculate its horizontal (Fx) and vertical (Fy) components.",
    "correct_answer": "Fx = 31.95 N, Fy = 22.37 N",
    "wrong_answers_pool": [
      "Fx = 22.37 N, Fy = 31.95 N",
      "Fx = 26.55 N, Fy = 24.14 N",
      "Fx = 28.91 N, Fy = 21.38 N",
      "Fx = 26.81 N, Fy = 18.35 N",
      "Fx = 31.24 N, Fy = 18.79 N",
      "Fx = 28.87 N, Fy = 25.53 N",
      "Fx = 37.84 N, Fy = 22.87 N",
      "Fx = 29.24 N, Fy = 21.86 N"
    ],
    "explanation": "Fx = F cos(\u03b8) = 39 cos(35\u00b0) = 31.95 N. Fy = F sin(\u03b8) = 39 sin(35\u00b0) = 22.37 N.",
    "exam_id": "EXAM_2026-W26_grade11_physical_sciences_paper1_39"
  },
  {
    "id": "PS11_P1_ELE_671",
    "topic": "Electricity (Electrostatics and Electric circuits)",
    "subtopic": "Coulomb's Law",
    "paper": "paper1",
    "difficulty": "medium",
    "question": "Two point charges of 8.0 \u03bcC and 12.0 \u03bcC are separated by a distance of 83.0 cm. Calculate the electrostatic force between them. (k = 9x10^9 N\u00b7m\u00b2/C\u00b2)",
    "correct_answer": "1.25",
    "wrong_answers_pool": [
      "0.12",
      "2.50",
      "11.25",
      "0.62",
      "12.50",
      "1.56"
    ],
    "explanation": "F = k * q1 * q2 / r\u00b2 = (9x10^9) * (8e-06) * (1.2e-05) / (0.83\u00b2) = 1.25 N.",
    "exam_id": "EXAM_2026-W26_grade11_physical_sciences_paper1_40"
  },
  {
    "id": "PS11_P1_WAV_466",
    "topic": "Waves, Sound and Light",
    "subtopic": "Snell's Law",
    "paper": "paper1",
    "difficulty": "medium",
    "question": "Light travels from a medium with refractive index 1.91 into a medium with refractive index 1.00. If the angle of incidence is 20\u00b0, calculate the angle of refraction.",
    "correct_answer": "40.5\u00b0",
    "wrong_answers_pool": [
      "30.50",
      "20.25",
      "81.00",
      "50.50",
      "4.05",
      "405.00"
    ],
    "explanation": "n1 * sin(\u03b81) = n2 * sin(\u03b82) => 1.91 * sin(20\u00b0) = 1.00 * sin(\u03b82) => \u03b82 = arcsin((1.91 * sin(20\u00b0)) / 1.00) = 40.5\u00b0.",
    "exam_id": "EXAM_2026-W26_grade11_physical_sciences_paper1_41"
  },
  {
    "id": "PS11_P1_MAG_941",
    "topic": "Magnetism and Electromagnetism",
    "subtopic": "Faraday's Law of Electromagnetic Induction",
    "paper": "paper1",
    "difficulty": "medium",
    "question": "A uniform magnetic field of 3.07 T passes perpendicular to a loop of area 214 cm\u00b2. Calculate the magnetic flux passing through the loop.",
    "correct_answer": "6.57x10^-02",
    "wrong_answers_pool": [
      "5.72x10^-04",
      "7.72x10^-04",
      "6.49x10^00",
      "7.17x10^00",
      "6.82x10^-03",
      "6.67x10^-04"
    ],
    "explanation": "\u03a6 = B * A * cos(0\u00b0) = 3.07 * 0.0214 * 1 = 6.57x10^-02 Wb.",
    "exam_id": "EXAM_2026-W26_grade11_physical_sciences_paper1_42"
  },
  {
    "id": "PS11_P1_WAV_751",
    "topic": "Waves, Sound and Light",
    "subtopic": "Critical angle and total internal reflection",
    "paper": "paper1",
    "difficulty": "hard",
    "question": "Calculate the critical angle for light passing from a medium with refractive index 2.29 into a medium with refractive index 1.53.",
    "correct_answer": "42.0\u00b0",
    "wrong_answers_pool": [
      "420.00",
      "52.00",
      "21.00",
      "4.20",
      "32.00",
      "84.00"
    ],
    "explanation": "sin(\u03b8_c) = n2 / n1 = 1.53 / 2.29. \u03b8_c = arcsin(1.53 / 2.29) = 42.0\u00b0.",
    "exam_id": "EXAM_2026-W26_grade11_physical_sciences_paper1_43"
  },
  {
    "id": "PS11_P1_WAV_730",
    "topic": "Waves, Sound and Light",
    "subtopic": "Critical angle and total internal reflection",
    "paper": "paper1",
    "difficulty": "hard",
    "question": "Calculate the critical angle for light passing from a medium with refractive index 1.96 into a medium with refractive index 1.11.",
    "correct_answer": "34.5\u00b0",
    "wrong_answers_pool": [
      "17.25",
      "345.00",
      "44.50",
      "24.50",
      "3.45",
      "69.00"
    ],
    "explanation": "sin(\u03b8_c) = n2 / n1 = 1.11 / 1.96. \u03b8_c = arcsin(1.11 / 1.96) = 34.5\u00b0.",
    "exam_id": "EXAM_2026-W26_grade11_physical_sciences_paper1_44"
  },
  {
    "id": "PS11_P1_ELE_353",
    "topic": "Electricity (Electrostatics and Electric circuits)",
    "subtopic": "Coulomb's Law",
    "paper": "paper1",
    "difficulty": "medium",
    "question": "Two point charges of 6.0 \u03bcC and 10.0 \u03bcC are separated by a distance of 69.0 cm. Calculate the electrostatic force between them. (k = 9x10^9 N\u00b7m\u00b2/C\u00b2)",
    "correct_answer": "1.13",
    "wrong_answers_pool": [
      "2.26",
      "0.11",
      "0.56",
      "11.13",
      "11.30",
      "1.28"
    ],
    "explanation": "F = k * q1 * q2 / r\u00b2 = (9x10^9) * (6e-06) * (9.999999999999999e-06) / (0.69\u00b2) = 1.13 N.",
    "exam_id": "EXAM_2026-W26_grade11_physical_sciences_paper1_45"
  },
  {
    "id": "PS11_P1_WAV_206",
    "topic": "Waves, Sound and Light",
    "subtopic": "Snell's Law",
    "paper": "paper1",
    "difficulty": "medium",
    "question": "Light travels from a medium with refractive index 1.78 into a medium with refractive index 1.64. If the angle of incidence is 45\u00b0, calculate the angle of refraction.",
    "correct_answer": "50.4\u00b0",
    "wrong_answers_pool": [
      "5.04",
      "60.40",
      "25.20",
      "504.00",
      "100.80",
      "40.40"
    ],
    "explanation": "n1 * sin(\u03b81) = n2 * sin(\u03b82) => 1.78 * sin(45\u00b0) = 1.64 * sin(\u03b82) => \u03b82 = arcsin((1.78 * sin(45\u00b0)) / 1.64) = 50.4\u00b0.",
    "exam_id": "EXAM_2026-W26_grade11_physical_sciences_paper1_46"
  },
  {
    "id": "PS11_P1_NEW_521",
    "topic": "Newton\u2019s Laws and Forces",
    "subtopic": "Newton's Law of Universal Gravitation",
    "paper": "paper1",
    "difficulty": "medium",
    "question": "Calculate the gravitational force of attraction between two masses, 785 kg and 92 kg, separated by a distance of 49 m. (G = 6.67x10^-11 N\u00b7m\u00b2/kg\u00b2)",
    "correct_answer": "2.01x10^-09",
    "wrong_answers_pool": [
      "3.76x10^-09",
      "1.04x10^-09",
      "2.12x10^-08",
      "1.63x10^-10",
      "2.20x10^-10",
      "2.36x10^-10"
    ],
    "explanation": "F = G * m1 * m2 / r\u00b2 = (6.67x10^-11) * 785 * 92 / 49\u00b2 = 2.01x10^-09 N.",
    "exam_id": "EXAM_2026-W26_grade11_physical_sciences_paper1_47"
  },
  {
    "id": "PS11_P1_MAG_151",
    "topic": "Magnetism and Electromagnetism",
    "subtopic": "Faraday's Law of Electromagnetic Induction",
    "paper": "paper1",
    "difficulty": "medium",
    "question": "A uniform magnetic field of 4.46 T passes perpendicular to a loop of area 430 cm\u00b2. Calculate the magnetic flux passing through the loop.",
    "correct_answer": "1.92x10^-01",
    "wrong_answers_pool": [
      "2.18x10^00",
      "1.56x10^01",
      "1.74x10^-02",
      "2.17x10^00",
      "2.06x10^-02",
      "2.05x10^01"
    ],
    "explanation": "\u03a6 = B * A * cos(0\u00b0) = 4.46 * 0.0430 * 1 = 1.92x10^-01 Wb.",
    "exam_id": "EXAM_2026-W26_grade11_physical_sciences_paper1_48"
  },
  {
    "id": "PS11_P1_WAV_678",
    "topic": "Waves, Sound and Light",
    "subtopic": "Critical angle and total internal reflection",
    "paper": "paper1",
    "difficulty": "hard",
    "question": "Calculate the critical angle for light passing from a medium with refractive index 2.21 into a medium with refractive index 1.59.",
    "correct_answer": "46.1\u00b0",
    "wrong_answers_pool": [
      "4.61",
      "23.05",
      "56.10",
      "36.10",
      "92.20",
      "461.00"
    ],
    "explanation": "sin(\u03b8_c) = n2 / n1 = 1.59 / 2.21. \u03b8_c = arcsin(1.59 / 2.21) = 46.1\u00b0.",
    "exam_id": "EXAM_2026-W26_grade11_physical_sciences_paper1_49"
  },
  {
    "id": "PS11_P1_WAV_685",
    "topic": "Waves, Sound and Light",
    "subtopic": "Critical angle and total internal reflection",
    "paper": "paper1",
    "difficulty": "hard",
    "question": "Calculate the critical angle for light passing from a medium with refractive index 1.96 into a medium with refractive index 1.75.",
    "correct_answer": "63.2\u00b0",
    "wrong_answers_pool": [
      "632.00",
      "31.60",
      "6.32",
      "126.40",
      "73.20",
      "53.20"
    ],
    "explanation": "sin(\u03b8_c) = n2 / n1 = 1.75 / 1.96. \u03b8_c = arcsin(1.75 / 1.96) = 63.2\u00b0.",
    "exam_id": "EXAM_2026-W26_grade11_physical_sciences_paper1_50"
  }
]