[
  {
    "id": "GEOM_238",
    "topic": "Euclidean Geometry",
    "subtopic": "triangle theorems",
    "difficulty": "medium",
    "question": "The exterior angle of a triangle is $84^\\circ$. If one of the opposite interior angles is $34^\\circ$, find the other opposite interior angle.",
    "correct_answer": "50^\\circ",
    "wrong_answers_pool": [
      "100^\\circ",
      "45^\\circ",
      "-50^\\circ",
      "46^\\circ",
      "48^\\circ",
      "49^\\circ",
      "47^\\circ",
      "51^\\circ"
    ],
    "explanation": "Exterior angle = sum of opposite interior angles. $84^\\circ = 34^\\circ + x \\implies x = 50^\\circ$.",
    "exam_id": "EXAM_2026-W20_grade12_mathematics_paper2_1"
  },
  {
    "id": "ANAGEO_994",
    "topic": "Analytical Geometry",
    "subtopic": "gradient of a line",
    "difficulty": "medium",
    "question": "Points A$(7; 1)$, B$(2; -3)$, and C$(7; y)$ are collinear. Find $y$.",
    "correct_answer": "1",
    "wrong_answers_pool": [
      "0",
      "2",
      "3",
      "8",
      "10",
      "-19",
      "-17",
      "15"
    ],
    "explanation": "Gradients are equal: $m_{AB} = \\frac{-3 - 1}{2 - 7} = 0.8$. Thus, $\\frac{y - -3}{7 - 2} = 0.8 \\implies y - -3 = 4.0 \\implies y = 1$.",
    "exam_id": "EXAM_2026-W20_grade12_mathematics_paper2_2"
  },
  {
    "id": "STAT_409",
    "topic": "Statistics and Regression",
    "subtopic": "standard deviation",
    "difficulty": "medium",
    "question": "For the dataset [13, 14, 17, 24, 22, 10, 18, 28, 18, 13], how many data points lie within one standard deviation of the mean?",
    "correct_answer": "7",
    "wrong_answers_pool": [
      "0",
      "1",
      "2",
      "3",
      "4",
      "5",
      "6",
      "8"
    ],
    "explanation": "Mean = $17.70$, Std Dev = $5.31$. The interval is $(12.39; 23.01)$. There are $7$ values in this interval.",
    "exam_id": "EXAM_2026-W20_grade12_mathematics_paper2_3"
  },
  {
    "id": "TRIG_682",
    "topic": "Trigonometry",
    "subtopic": "cosine rule",
    "difficulty": "medium",
    "question": "In $\\Delta ABC$, $a = 5$, $b = 13$, and $c = 12$. Find the size of $\\angle C$ (to 1 decimal place).",
    "correct_answer": "67.4^\\circ",
    "wrong_answers_pool": [
      "0.0^\\circ",
      "33.7^\\circ",
      "66.4^\\circ",
      "67.0^\\circ",
      "68.4^\\circ",
      "101.1^\\circ",
      "134.8^\\circ",
      "70.1^\\circ"
    ],
    "explanation": "$\\cos C = \\frac{a^2 + b^2 - c^2}{2ab} = \\frac{5^2 + 13^2 - 12^2}{2(5)(13)} = 0.3846 \\implies C \\approx 67.4^\\circ$.",
    "exam_id": "EXAM_2026-W20_grade12_mathematics_paper2_4"
  },
  {
    "id": "ANAGEO_812",
    "topic": "Analytical Geometry",
    "subtopic": "distance formula",
    "difficulty": "medium",
    "question": "Find the distance between points A$(-4; 1)$ and B$(2; 0)$ correct to two decimal places.",
    "correct_answer": "6.08",
    "wrong_answers_pool": [
      "6.32",
      "2.23",
      "9.73",
      "4.30",
      "10.70",
      "4.20",
      "5.04",
      "6.22"
    ],
    "explanation": "$d = \\sqrt{(2 - -4)^2 + (0 - 1)^2} = \\sqrt{37} \\approx 6.08$.",
    "exam_id": "EXAM_2026-W20_grade12_mathematics_paper2_5"
  },
  {
    "id": "STAT_811",
    "topic": "Statistics and Regression",
    "subtopic": "mean, median, mode",
    "difficulty": "medium",
    "question": "Determine the median of the following dataset: [39, 50, 24, 38, 33].",
    "correct_answer": "38",
    "wrong_answers_pool": [
      "39",
      "24",
      "33.5",
      "25",
      "33",
      "39.5",
      "24.5",
      "50.5"
    ],
    "explanation": "First, sort the data: [24, 33, 38, 39, 50]. The median is the middle value: $38$.",
    "exam_id": "EXAM_2026-W20_grade12_mathematics_paper2_6"
  },
  {
    "id": "ANAGEO_277",
    "topic": "Analytical Geometry",
    "subtopic": "distance formula",
    "difficulty": "hard",
    "question": "The distance between A$(5; -2)$ and B$(x; 7)$ is $\\sqrt{85}$. Find the possible value(s) of $x$.",
    "correct_answer": "3, 7",
    "wrong_answers_pool": [
      "-2, 1",
      "-15, -1",
      "6, 9",
      "-4, -3",
      "-2, 9",
      "3, 8",
      "2, 6",
      "-9, 3"
    ],
    "explanation": "$\\sqrt{(x - 5)^2 + (7 - -2)^2} = \\sqrt{85} \\implies (x - 5)^2 + 81 = 85 \\implies (x - 5)^2 = 4 \\implies x - 5 = \\pm 2 \\implies x = 7$ or $x = 3$.",
    "exam_id": "EXAM_2026-W20_grade12_mathematics_paper2_7"
  },
  {
    "id": "TRIG_763",
    "topic": "Trigonometry",
    "subtopic": "cosine rule",
    "difficulty": "medium",
    "question": "In $\\Delta ABC$, $a = 14$, $b = 10$, and $c = 19$. Find the size of $\\angle C$ (to 1 decimal place).",
    "correct_answer": "103.4^\\circ",
    "wrong_answers_pool": [
      "0.0^\\circ",
      "89.2^\\circ",
      "121.2^\\circ",
      "102.4^\\circ",
      "104.4^\\circ",
      "107.7^\\circ",
      "107.2^\\circ",
      "206.8^\\circ"
    ],
    "explanation": "$\\cos C = \\frac{a^2 + b^2 - c^2}{2ab} = \\frac{14^2 + 10^2 - 19^2}{2(14)(10)} = -0.2321 \\implies C \\approx 103.4^\\circ$.",
    "exam_id": "EXAM_2026-W20_grade12_mathematics_paper2_8"
  },
  {
    "id": "STAT_805",
    "topic": "Statistics and Regression",
    "subtopic": "linear regression",
    "difficulty": "medium",
    "question": "Given the bivariate data: x = [1, 2, 3, 4, 5, 6, 7], y = [4.3, 3.3, 4.8, 3.3, 1.2, -0.9, -0.8]. Calculate the gradient ($b$) of the least squares regression line $\\hat{y} = a + bx$ (correct to 2 decimal places).",
    "correct_answer": "-0.97",
    "wrong_answers_pool": [
      "0.97",
      "-0.49",
      "0.03",
      "6.06",
      "8.76",
      "-1.97",
      "-1.95",
      "-1.03"
    ],
    "explanation": "Using a calculator (STAT mode), enter the data points. The gradient $b \\approx -0.97$.",
    "exam_id": "EXAM_2026-W20_grade12_mathematics_paper2_9"
  },
  {
    "id": "GEOM_040",
    "topic": "Euclidean Geometry",
    "subtopic": "triangle theorems",
    "difficulty": "hard",
    "question": "In an isosceles triangle, the two equal base angles each measure $(2x + 12)^\\circ$. The vertex angle measures $(2x + 96)^\\circ$. Find the value of $x$.",
    "correct_answer": "10",
    "wrong_answers_pool": [
      "3",
      "5",
      "8",
      "9",
      "11",
      "12",
      "14",
      "17"
    ],
    "explanation": "Sum of angles is $180^\\circ$. $2(2x + 12) + (2x + 96) = 180 \\implies 6x + 120 = 180 \\implies 6x = 60 \\implies x = 10$.",
    "exam_id": "EXAM_2026-W20_grade12_mathematics_paper2_10"
  },
  {
    "id": "STAT_509",
    "topic": "Statistics and Regression",
    "subtopic": "mean, median, mode",
    "difficulty": "medium",
    "question": "Determine the median of the following dataset: [50, 22, 42, 18, 27, 17].",
    "correct_answer": "24.5",
    "wrong_answers_pool": [
      "51",
      "28",
      "42",
      "17.5",
      "18",
      "17",
      "16",
      "26"
    ],
    "explanation": "First, sort the data: [17, 18, 22, 27, 42, 50]. The median is the middle value: $24.5$.",
    "exam_id": "EXAM_2026-W20_grade12_mathematics_paper2_11"
  },
  {
    "id": "ANAGEO_298",
    "topic": "Analytical Geometry",
    "subtopic": "midpoint formula",
    "difficulty": "hard",
    "question": "A$(-1; 7)$, B$(6; 5)$, C$(1; -2)$, and D$(x; y)$ are the vertices of a parallelogram ABCD. Determine the coordinates of D.",
    "correct_answer": "(-6; 0)",
    "wrong_answers_pool": [
      "(-8; -4)",
      "(-5; 1)",
      "(-4; 3)",
      "(-10; 1)",
      "(-2; -4)",
      "(-4; -2)",
      "(-1; 1)",
      "(-10; -5)"
    ],
    "explanation": "Diagonals bisect each other. Midpoint AC = Midpoint BD. $\\frac{-1+1}{2} = \\frac{6+x}{2} \\implies x = -6$. $\\frac{7+-2}{2} = \\frac{5+y}{2} \\implies y = 0$.",
    "exam_id": "EXAM_2026-W20_grade12_mathematics_paper2_12"
  },
  {
    "id": "ANAGEO_250",
    "topic": "Analytical Geometry",
    "subtopic": "gradient of a line",
    "difficulty": "hard",
    "question": "Line AB passes through A$(-6; 0)$ and B$(0; 6)$. Line CD passes through C$(0; -1)$ and D$(6; y)$. If AB $\\perp$ CD, find $y$.",
    "correct_answer": "-7",
    "wrong_answers_pool": [
      "-27",
      "7",
      "-24",
      "10",
      "-21",
      "-22",
      "-14",
      "-9"
    ],
    "explanation": "$m_{AB} = \\frac{6 - 0}{0 - -6} = 1.0$. For perpendicular lines, $m_{CD} = -\\frac{1}{m_{AB}} = -1.0$. $\\frac{y - -1}{6 - 0} = -1.0 \\implies y = -7$.",
    "exam_id": "EXAM_2026-W20_grade12_mathematics_paper2_13"
  },
  {
    "id": "TRIG_476",
    "topic": "Trigonometry",
    "subtopic": "sine rule",
    "difficulty": "medium",
    "question": "In $\\Delta ABC$, $a = 18$, $b = 15$, and $\\angle A = 70^\\circ$. Find the size of acute $\\angle B$ (to 1 decimal place).",
    "correct_answer": "51.5^\\circ",
    "wrong_answers_pool": [
      "0.0^\\circ",
      "32.9^\\circ",
      "103.0^\\circ",
      "39.7^\\circ",
      "44.9^\\circ",
      "-51.5^\\circ",
      "77.2^\\circ",
      "46.8^\\circ"
    ],
    "explanation": "$\\frac{\\sin B}{b} = \\frac{\\sin A}{a} \\implies \\sin B = \\frac{15 \\cdot \\sin 70^\\circ}{18} \\approx 0.7831 \\implies B \\approx 51.5^\\circ$.",
    "exam_id": "EXAM_2026-W20_grade12_mathematics_paper2_14"
  },
  {
    "id": "ANAGEO_400",
    "topic": "Analytical Geometry",
    "subtopic": "distance formula",
    "difficulty": "hard",
    "question": "The distance between A$(5; 1)$ and B$(x; -4)$ is $\\sqrt{89}$. Find the possible value(s) of $x$.",
    "correct_answer": "-3, 13",
    "wrong_answers_pool": [
      "-10, -7",
      "9",
      "-10, -2",
      "-15, 3",
      "-13, 14",
      "-9, -8",
      "5, 9",
      "-10, 1"
    ],
    "explanation": "$\\sqrt{(x - 5)^2 + (-4 - 1)^2} = \\sqrt{89} \\implies (x - 5)^2 + 25 = 89 \\implies (x - 5)^2 = 64 \\implies x - 5 = \\pm 8 \\implies x = 13$ or $x = -3$.",
    "exam_id": "EXAM_2026-W20_grade12_mathematics_paper2_15"
  },
  {
    "id": "GEOM_872",
    "topic": "Euclidean Geometry",
    "subtopic": "angle relationships",
    "difficulty": "medium",
    "question": "Two vertically opposite angles measure $(3x + 31)^\\circ$ and $(1x +87)^\\circ$. Find the value of $x$.",
    "correct_answer": "28",
    "wrong_answers_pool": [
      "32",
      "-28",
      "41",
      "14",
      "17",
      "19",
      "84",
      "56"
    ],
    "explanation": "Vertically opposite angles are equal: $3x + 31 = 1x +87 \\implies 2x = 56 \\implies x = 28$.",
    "exam_id": "EXAM_2026-W20_grade12_mathematics_paper2_16"
  },
  {
    "id": "STAT_561",
    "topic": "Statistics and Regression",
    "subtopic": "linear regression",
    "difficulty": "hard",
    "question": "The equation of the least squares regression line for a dataset is $\\hat{y} = -3.24 -3.23x$. Predict the value of $y$ when $x = 11$ (correct to 2 decimal places).",
    "correct_answer": "-38.78",
    "wrong_answers_pool": [
      "-0.03",
      "-58.16",
      "38.78",
      "-25.89",
      "-24.37",
      "-37.89",
      "-19.39",
      "-51.73"
    ],
    "explanation": "Substitute $x = 11$ into the equation: $\\hat{y} = -3.24 -3.23(11) \\approx -38.78$.",
    "exam_id": "EXAM_2026-W20_grade12_mathematics_paper2_17"
  },
  {
    "id": "STAT_184",
    "topic": "Statistics and Regression",
    "subtopic": "mean, median, mode",
    "difficulty": "medium",
    "question": "Determine the median of the following dataset: [25, 34, 42, 39, 46, 14].",
    "correct_answer": "36.5",
    "wrong_answers_pool": [
      "39",
      "42.5",
      "25",
      "34.5",
      "45",
      "33",
      "40",
      "25.5"
    ],
    "explanation": "First, sort the data: [14, 25, 34, 39, 42, 46]. The median is the middle value: $36.5$.",
    "exam_id": "EXAM_2026-W20_grade12_mathematics_paper2_18"
  },
  {
    "id": "STAT_540",
    "topic": "Statistics and Regression",
    "subtopic": "linear regression",
    "difficulty": "hard",
    "question": "The equation of the least squares regression line for a dataset is $\\hat{y} = 3.43 +1.75x$. Predict the value of $y$ when $x = 8$ (correct to 2 decimal places).",
    "correct_answer": "17.43",
    "wrong_answers_pool": [
      "0.06",
      "1.94",
      "34.86",
      "0.27",
      "0.72",
      "33.67",
      "8.71",
      "-17.43"
    ],
    "explanation": "Substitute $x = 8$ into the equation: $\\hat{y} = 3.43 +1.75(8) \\approx 17.43$.",
    "exam_id": "EXAM_2026-W20_grade12_mathematics_paper2_19"
  },
  {
    "id": "GEOM_216",
    "topic": "Euclidean Geometry",
    "subtopic": "triangle theorems",
    "difficulty": "medium",
    "question": "The exterior angle of a triangle is $89^\\circ$. If one of the opposite interior angles is $38^\\circ$, find the other opposite interior angle.",
    "correct_answer": "51^\\circ",
    "wrong_answers_pool": [
      "153^\\circ",
      "66^\\circ",
      "69^\\circ",
      "102^\\circ",
      "40^\\circ",
      "-51^\\circ",
      "48^\\circ",
      "49^\\circ"
    ],
    "explanation": "Exterior angle = sum of opposite interior angles. $89^\\circ = 38^\\circ + x \\implies x = 51^\\circ$.",
    "exam_id": "EXAM_2026-W20_grade12_mathematics_paper2_20"
  },
  {
    "id": "TRIG_875",
    "topic": "Trigonometry",
    "subtopic": "sine rule",
    "difficulty": "medium",
    "question": "In $\\Delta ABC$, $a = 13$, $b = 10$, and $\\angle A = 91^\\circ$. Find the size of acute $\\angle B$ (to 1 decimal place).",
    "correct_answer": "50.3^\\circ",
    "wrong_answers_pool": [
      "0.0^\\circ",
      "67.3^\\circ",
      "100.6^\\circ",
      "36.2^\\circ",
      "75.4^\\circ",
      "-50.3^\\circ",
      "47.1^\\circ",
      "49.3^\\circ"
    ],
    "explanation": "$\\frac{\\sin B}{b} = \\frac{\\sin A}{a} \\implies \\sin B = \\frac{10 \\cdot \\sin 91^\\circ}{13} \\approx 0.7691 \\implies B \\approx 50.3^\\circ$.",
    "exam_id": "EXAM_2026-W20_grade12_mathematics_paper2_21"
  },
  {
    "id": "GEOM_333",
    "topic": "Euclidean Geometry",
    "subtopic": "angle relationships",
    "difficulty": "hard",
    "question": "Two parallel lines are intersected by a transversal. A pair of co-interior angles are $(6x + 7)^\\circ$ and $(6x + 5)^\\circ$. Find the size of the larger angle.",
    "correct_answer": "91^\\circ",
    "wrong_answers_pool": [
      "100^\\circ",
      "-91^\\circ",
      "73^\\circ",
      "74^\\circ",
      "76^\\circ",
      "45^\\circ",
      "273^\\circ",
      "84^\\circ"
    ],
    "explanation": "Co-interior angles between parallel lines are supplementary. $6x + 7 + 6x + 5 = 180 \\implies 12x = 168 \\implies x = 14$. The angles are $91^\\circ$ and $89^\\circ$, so the larger is $91^\\circ$.",
    "exam_id": "EXAM_2026-W20_grade12_mathematics_paper2_22"
  },
  {
    "id": "GEOM_737",
    "topic": "Euclidean Geometry",
    "subtopic": "triangle theorems",
    "difficulty": "hard",
    "question": "In an isosceles triangle, the two equal base angles each measure $(2x + 14)^\\circ$. The vertex angle measures $(3x + 54)^\\circ$. Find the value of $x$.",
    "correct_answer": "14",
    "wrong_answers_pool": [
      "0",
      "32",
      "2",
      "7",
      "8",
      "42",
      "11",
      "12"
    ],
    "explanation": "Sum of angles is $180^\\circ$. $2(2x + 14) + (3x + 54) = 180 \\implies 7x + 82 = 180 \\implies 7x = 98 \\implies x = 14$.",
    "exam_id": "EXAM_2026-W20_grade12_mathematics_paper2_23"
  },
  {
    "id": "TRIG_130",
    "topic": "Trigonometry",
    "subtopic": "sine rule",
    "difficulty": "medium",
    "question": "In $\\Delta ABC$, $a = 10$, $b = 7$, and $\\angle A = 90^\\circ$. Find the size of acute $\\angle B$ (to 1 decimal place).",
    "correct_answer": "44.4^\\circ",
    "wrong_answers_pool": [
      "0.0^\\circ",
      "66.6^\\circ",
      "35.7^\\circ",
      "36.6^\\circ",
      "39.8^\\circ",
      "41.5^\\circ",
      "43.4^\\circ",
      "44.9^\\circ"
    ],
    "explanation": "$\\frac{\\sin B}{b} = \\frac{\\sin A}{a} \\implies \\sin B = \\frac{7 \\cdot \\sin 90^\\circ}{10} \\approx 0.7000 \\implies B \\approx 44.4^\\circ$.",
    "exam_id": "EXAM_2026-W20_grade12_mathematics_paper2_24"
  },
  {
    "id": "STAT_496",
    "topic": "Statistics and Regression",
    "subtopic": "standard deviation",
    "difficulty": "medium",
    "question": "For the dataset [13, 10, 18, 19, 28, 26, 21, 30, 12, 11], how many data points lie within one standard deviation of the mean?",
    "correct_answer": "5",
    "wrong_answers_pool": [
      "0",
      "1",
      "2",
      "3",
      "4",
      "6",
      "7",
      "8"
    ],
    "explanation": "Mean = $18.80$, Std Dev = $6.97$. The interval is $(11.83; 25.77)$. There are $5$ values in this interval.",
    "exam_id": "EXAM_2026-W20_grade12_mathematics_paper2_25"
  },
  {
    "id": "TRIG_199",
    "topic": "Trigonometry",
    "subtopic": "cosine rule",
    "difficulty": "hard",
    "question": "In $\\Delta ABC$, $a = 13$, $\\angle B = 49^\\circ$, and $\\angle C = 80^\\circ$. Calculate the area of the triangle (to 1 decimal place).",
    "correct_answer": "80.8",
    "wrong_answers_pool": [
      "0.0",
      "161.6",
      "40.4",
      "76.2",
      "77.4",
      "79.8",
      "-80.8",
      "81.8"
    ],
    "explanation": "$\\angle A = 180^\\circ - (49^\\circ + 80^\\circ) = 51^\\circ$. By Sine Rule, $c = \\frac{13\\sin 80^\\circ}{\\sin 51^\\circ} \\approx 16.47$. Area = $\\frac{1}{2}ac\\sin B \\approx 80.8$.",
    "exam_id": "EXAM_2026-W20_grade12_mathematics_paper2_26"
  },
  {
    "id": "STAT_159",
    "topic": "Statistics and Regression",
    "subtopic": "standard deviation",
    "difficulty": "hard",
    "question": "A dataset has a standard deviation of $5$. If every value in the dataset is multiplied by $2$ and then $16$ is added, what is the new standard deviation?",
    "correct_answer": "10",
    "wrong_answers_pool": [
      "21",
      "26",
      "5",
      "7",
      "80",
      "100",
      "160",
      "23"
    ],
    "explanation": "Adding a constant does not change the standard deviation. Multiplying by a constant $k$ multiplies the standard deviation by $|k|$. New std dev = $5 \\times 2 = 10$.",
    "exam_id": "EXAM_2026-W20_grade12_mathematics_paper2_27"
  },
  {
    "id": "ANAGEO_070",
    "topic": "Analytical Geometry",
    "subtopic": "midpoint formula",
    "difficulty": "medium",
    "question": "The midpoint of line segment AB is M$(-8.5; -1)$. If A is $(-7; 0)$, find the coordinates of B.",
    "correct_answer": "(-10; -2)",
    "wrong_answers_pool": [
      "(-9; -3)",
      "(-12; -6)",
      "(-8; -5)",
      "(-14; -7)",
      "(-12; 1)",
      "(-10; -7)",
      "(-9; 1)",
      "(-11; -3)"
    ],
    "explanation": "$\\frac{-7 + x_2}{2} = -8.5 \\implies x_2 = -10$. $\\frac{0 + y_2}{2} = -1 \\implies y_2 = -2$.",
    "exam_id": "EXAM_2026-W20_grade12_mathematics_paper2_28"
  },
  {
    "id": "GEOM_764",
    "topic": "Euclidean Geometry",
    "subtopic": "angle relationships",
    "difficulty": "hard",
    "question": "Two parallel lines are intersected by a transversal. A pair of co-interior angles are $(3x + 12)^\\circ$ and $(2x + 8)^\\circ$. Find the size of the larger angle.",
    "correct_answer": "108^\\circ",
    "wrong_answers_pool": [
      "324^\\circ",
      "105^\\circ",
      "106^\\circ",
      "107^\\circ",
      "109^\\circ",
      "110^\\circ",
      "-108^\\circ",
      "54^\\circ"
    ],
    "explanation": "Co-interior angles between parallel lines are supplementary. $3x + 12 + 2x + 8 = 180 \\implies 5x = 160 \\implies x = 32$. The angles are $108^\\circ$ and $72^\\circ$, so the larger is $108^\\circ$.",
    "exam_id": "EXAM_2026-W20_grade12_mathematics_paper2_29"
  },
  {
    "id": "GEOM_811",
    "topic": "Euclidean Geometry",
    "subtopic": "triangle theorems",
    "difficulty": "hard",
    "question": "In an isosceles triangle, the two equal base angles each measure $(3x + 12)^\\circ$. The vertex angle measures $(1x + 9)^\\circ$. Find the value of $x$.",
    "correct_answer": "21",
    "wrong_answers_pool": [
      "32",
      "38",
      "10",
      "42",
      "-21",
      "15",
      "18",
      "19"
    ],
    "explanation": "Sum of angles is $180^\\circ$. $2(3x + 12) + (1x + 9) = 180 \\implies 7x + 33 = 180 \\implies 7x = 147 \\implies x = 21$.",
    "exam_id": "EXAM_2026-W20_grade12_mathematics_paper2_30"
  },
  {
    "id": "GEOM_826",
    "topic": "Euclidean Geometry",
    "subtopic": "triangle theorems",
    "difficulty": "medium",
    "question": "The exterior angle of a triangle is $103^\\circ$. If one of the opposite interior angles is $35^\\circ$, find the other opposite interior angle.",
    "correct_answer": "68^\\circ",
    "wrong_answers_pool": [
      "34^\\circ",
      "67^\\circ",
      "66^\\circ",
      "69^\\circ",
      "70^\\circ",
      "136^\\circ",
      "204^\\circ",
      "80^\\circ"
    ],
    "explanation": "Exterior angle = sum of opposite interior angles. $103^\\circ = 35^\\circ + x \\implies x = 68^\\circ$.",
    "exam_id": "EXAM_2026-W20_grade12_mathematics_paper2_31"
  },
  {
    "id": "STAT_151",
    "topic": "Statistics and Regression",
    "subtopic": "standard deviation",
    "difficulty": "hard",
    "question": "A dataset has a standard deviation of $4$. If every value in the dataset is multiplied by $4$ and then $19$ is added, what is the new standard deviation?",
    "correct_answer": "16",
    "wrong_answers_pool": [
      "23",
      "35",
      "4",
      "8",
      "76",
      "256",
      "304",
      "27"
    ],
    "explanation": "Adding a constant does not change the standard deviation. Multiplying by a constant $k$ multiplies the standard deviation by $|k|$. New std dev = $4 \\times 4 = 16$.",
    "exam_id": "EXAM_2026-W20_grade12_mathematics_paper2_32"
  },
  {
    "id": "ANAGEO_018",
    "topic": "Analytical Geometry",
    "subtopic": "distance formula",
    "difficulty": "hard",
    "question": "The distance between A$(1; -10)$ and B$(x; 0)$ is $\\sqrt{104}$. Find the possible value(s) of $x$.",
    "correct_answer": "-1, 3",
    "wrong_answers_pool": [
      "-12, -3",
      "3, 13",
      "2, 13",
      "-13, 14",
      "-5, -1",
      "1, 3",
      "3, 8",
      "9, 10"
    ],
    "explanation": "$\\sqrt{(x - 1)^2 + (0 - -10)^2} = \\sqrt{104} \\implies (x - 1)^2 + 100 = 104 \\implies (x - 1)^2 = 4 \\implies x - 1 = \\pm 2 \\implies x = 3$ or $x = -1$.",
    "exam_id": "EXAM_2026-W20_grade12_mathematics_paper2_33"
  },
  {
    "id": "ANAGEO_925",
    "topic": "Analytical Geometry",
    "subtopic": "midpoint formula",
    "difficulty": "medium",
    "question": "The midpoint of line segment AB is M$(3; -2.5)$. If A is $(-4; -5)$, find the coordinates of B.",
    "correct_answer": "(10; 0)",
    "wrong_answers_pool": [
      "(8; 3)",
      "(5; -5)",
      "(8; -2)",
      "(13; 5)",
      "(11; 0)",
      "(15; -4)",
      "(13; -5)",
      "(13; -1)"
    ],
    "explanation": "$\\frac{-4 + x_2}{2} = 3 \\implies x_2 = 10$. $\\frac{-5 + y_2}{2} = -2.5 \\implies y_2 = 0$.",
    "exam_id": "EXAM_2026-W20_grade12_mathematics_paper2_34"
  },
  {
    "id": "TRIG_997",
    "topic": "Trigonometry",
    "subtopic": "cosine rule",
    "difficulty": "medium",
    "question": "In $\\Delta ABC$, $a = 13$, $b = 6$, and $c = 17$. Find the size of $\\angle C$ (to 1 decimal place).",
    "correct_answer": "122.6^\\circ",
    "wrong_answers_pool": [
      "0.0^\\circ",
      "-122.6^\\circ",
      "107.7^\\circ",
      "112.8^\\circ",
      "119.0^\\circ",
      "245.2^\\circ",
      "125.7^\\circ",
      "183.9^\\circ"
    ],
    "explanation": "$\\cos C = \\frac{a^2 + b^2 - c^2}{2ab} = \\frac{13^2 + 6^2 - 17^2}{2(13)(6)} = -0.5385 \\implies C \\approx 122.6^\\circ$.",
    "exam_id": "EXAM_2026-W20_grade12_mathematics_paper2_35"
  },
  {
    "id": "TRIG_440",
    "topic": "Trigonometry",
    "subtopic": "cosine rule",
    "difficulty": "hard",
    "question": "In $\\Delta ABC$, $a = 18$, $\\angle B = 30^\\circ$, and $\\angle C = 68^\\circ$. Calculate the area of the triangle (to 1 decimal place).",
    "correct_answer": "75.8",
    "wrong_answers_pool": [
      "0.0",
      "65.3",
      "66.8",
      "37.9",
      "73.1",
      "74.8",
      "76.8",
      "113.7"
    ],
    "explanation": "$\\angle A = 180^\\circ - (30^\\circ + 68^\\circ) = 82^\\circ$. By Sine Rule, $c = \\frac{18\\sin 68^\\circ}{\\sin 82^\\circ} \\approx 16.85$. Area = $\\frac{1}{2}ac\\sin B \\approx 75.8$.",
    "exam_id": "EXAM_2026-W20_grade12_mathematics_paper2_36"
  },
  {
    "id": "GEOM_629",
    "topic": "Euclidean Geometry",
    "subtopic": "angle relationships",
    "difficulty": "hard",
    "question": "Two parallel lines are intersected by a transversal. A pair of co-interior angles are $(3x + 16)^\\circ$ and $(4x + 17)^\\circ$. Find the size of the larger angle.",
    "correct_answer": "101^\\circ",
    "wrong_answers_pool": [
      "99^\\circ",
      "100^\\circ",
      "102^\\circ",
      "103^\\circ",
      "202^\\circ",
      "107^\\circ",
      "109^\\circ",
      "303^\\circ"
    ],
    "explanation": "Co-interior angles between parallel lines are supplementary. $3x + 16 + 4x + 17 = 180 \\implies 7x = 147 \\implies x = 21$. The angles are $79^\\circ$ and $101^\\circ$, so the larger is $101^\\circ$.",
    "exam_id": "EXAM_2026-W20_grade12_mathematics_paper2_37"
  },
  {
    "id": "GEOM_420",
    "topic": "Euclidean Geometry",
    "subtopic": "triangle theorems",
    "difficulty": "hard",
    "question": "In an isosceles triangle, the two equal base angles each measure $(2x + 10)^\\circ$. The vertex angle measures $(3x + 62)^\\circ$. Find the value of $x$.",
    "correct_answer": "14",
    "wrong_answers_pool": [
      "1",
      "5",
      "7",
      "9",
      "42",
      "12",
      "13",
      "15"
    ],
    "explanation": "Sum of angles is $180^\\circ$. $2(2x + 10) + (3x + 62) = 180 \\implies 7x + 82 = 180 \\implies 7x = 98 \\implies x = 14$.",
    "exam_id": "EXAM_2026-W20_grade12_mathematics_paper2_38"
  },
  {
    "id": "TRIG_079",
    "topic": "Trigonometry",
    "subtopic": "cosine rule",
    "difficulty": "hard",
    "question": "In $\\Delta ABC$, $a = 9$, $\\angle B = 31^\\circ$, and $\\angle C = 55^\\circ$. Calculate the area of the triangle (to 1 decimal place).",
    "correct_answer": "17.1",
    "wrong_answers_pool": [
      "0.1",
      "34.2",
      "4.8",
      "8.6",
      "12.6",
      "14.3",
      "-17.1",
      "16.1"
    ],
    "explanation": "$\\angle A = 180^\\circ - (31^\\circ + 55^\\circ) = 94^\\circ$. By Sine Rule, $c = \\frac{9\\sin 55^\\circ}{\\sin 94^\\circ} \\approx 7.39$. Area = $\\frac{1}{2}ac\\sin B \\approx 17.1$.",
    "exam_id": "EXAM_2026-W20_grade12_mathematics_paper2_39"
  },
  {
    "id": "STAT_787",
    "topic": "Statistics and Regression",
    "subtopic": "scatter plots",
    "difficulty": "medium",
    "question": "Given the bivariate data: x = [1, 2, 3, 4, 5, 6, 7], y = [11.6, 13.3, 13.1, 13.3, 17.4, 18.2, 19.8]. Calculate the gradient ($b$) of the least squares regression line $\\hat{y} = a + bx$ (correct to 2 decimal places).",
    "correct_answer": "1.38",
    "wrong_answers_pool": [
      "0.38",
      "0.69",
      "2.38",
      "2.07",
      "2.76",
      "0.72",
      "4.40",
      "11.96"
    ],
    "explanation": "Using a calculator (STAT mode), enter the data points. The gradient $b \\approx 1.38$.",
    "exam_id": "EXAM_2026-W20_grade12_mathematics_paper2_40"
  },
  {
    "id": "ANAGEO_816",
    "topic": "Analytical Geometry",
    "subtopic": "gradient of a line",
    "difficulty": "medium",
    "question": "Points A$(9; 7)$, B$(5; -1)$, and C$(6; y)$ are collinear. Find $y$.",
    "correct_answer": "1",
    "wrong_answers_pool": [
      "0",
      "2",
      "3",
      "7",
      "13",
      "-18",
      "16",
      "19"
    ],
    "explanation": "Gradients are equal: $m_{AB} = \\frac{-1 - 7}{5 - 9} = 2.0$. Thus, $\\frac{y - -1}{6 - 5} = 2.0 \\implies y - -1 = 2.0 \\implies y = 1$.",
    "exam_id": "EXAM_2026-W20_grade12_mathematics_paper2_41"
  },
  {
    "id": "ANAGEO_432",
    "topic": "Analytical Geometry",
    "subtopic": "gradient of a line",
    "difficulty": "hard",
    "question": "Line AB passes through A$(3; 4)$ and B$(10; -10)$. Line CD passes through C$(-2; 3)$ and D$(-16; y)$. If AB $\\perp$ CD, find $y$.",
    "correct_answer": "-4",
    "wrong_answers_pool": [
      "0",
      "3",
      "4",
      "9",
      "11",
      "13",
      "-19",
      "-12"
    ],
    "explanation": "$m_{AB} = \\frac{-10 - 4}{10 - 3} = -2.0$. For perpendicular lines, $m_{CD} = -\\frac{1}{m_{AB}} = 0.5$. $\\frac{y - 3}{-16 - -2} = 0.5 \\implies y = -4$.",
    "exam_id": "EXAM_2026-W20_grade12_mathematics_paper2_42"
  },
  {
    "id": "TRIG_592",
    "topic": "Trigonometry",
    "subtopic": "cosine rule",
    "difficulty": "medium",
    "question": "In $\\Delta ABC$, $a = 13$, $b = 5$, and $c = 12$. Find the size of $\\angle C$ (to 1 decimal place).",
    "correct_answer": "67.4^\\circ",
    "wrong_answers_pool": [
      "0.0^\\circ",
      "33.7^\\circ",
      "66.4^\\circ",
      "68.4^\\circ",
      "101.1^\\circ",
      "134.8^\\circ",
      "72.5^\\circ",
      "47.5^\\circ"
    ],
    "explanation": "$\\cos C = \\frac{a^2 + b^2 - c^2}{2ab} = \\frac{13^2 + 5^2 - 12^2}{2(13)(5)} = 0.3846 \\implies C \\approx 67.4^\\circ$.",
    "exam_id": "EXAM_2026-W20_grade12_mathematics_paper2_43"
  },
  {
    "id": "GEOM_591",
    "topic": "Euclidean Geometry",
    "subtopic": "angle relationships",
    "difficulty": "hard",
    "question": "Two parallel lines are intersected by a transversal. A pair of co-interior angles are $(4x + 8)^\\circ$ and $(4x + 20)^\\circ$. Find the size of the larger angle.",
    "correct_answer": "96^\\circ",
    "wrong_answers_pool": [
      "-96^\\circ",
      "97^\\circ",
      "192^\\circ",
      "98^\\circ",
      "288^\\circ",
      "109^\\circ",
      "48^\\circ",
      "82^\\circ"
    ],
    "explanation": "Co-interior angles between parallel lines are supplementary. $4x + 8 + 4x + 20 = 180 \\implies 8x = 152 \\implies x = 19$. The angles are $84^\\circ$ and $96^\\circ$, so the larger is $96^\\circ$.",
    "exam_id": "EXAM_2026-W20_grade12_mathematics_paper2_44"
  },
  {
    "id": "GEOM_037",
    "topic": "Euclidean Geometry",
    "subtopic": "triangle theorems",
    "difficulty": "hard",
    "question": "In an isosceles triangle, the two equal base angles each measure $(2x + 14)^\\circ$. The vertex angle measures $(1x + 2)^\\circ$. Find the value of $x$.",
    "correct_answer": "30",
    "wrong_answers_pool": [
      "32",
      "-30",
      "35",
      "26",
      "36",
      "43",
      "44",
      "28"
    ],
    "explanation": "Sum of angles is $180^\\circ$. $2(2x + 14) + (1x + 2) = 180 \\implies 5x + 30 = 180 \\implies 5x = 150 \\implies x = 30$.",
    "exam_id": "EXAM_2026-W20_grade12_mathematics_paper2_45"
  },
  {
    "id": "ANAGEO_195",
    "topic": "Analytical Geometry",
    "subtopic": "equation of a line",
    "difficulty": "medium",
    "question": "Find the equation of the line passing through $(-2; -1)$ and parallel to the line $y = 0x + 4$.",
    "correct_answer": "y = 0x - 1",
    "wrong_answers_pool": [
      "y = 1x - 4",
      "y = -2x + 0",
      "y = -2x + 4",
      "y = -1x - 2",
      "y = 0x + 2",
      "y = 0x + 4",
      "y = -1x - 4",
      "y = -1x - 6"
    ],
    "explanation": "Parallel lines have the same gradient $m = 0$. Equation is $y - -1 = 0(x - -2) \\implies y = 0x - 1$.",
    "exam_id": "EXAM_2026-W20_grade12_mathematics_paper2_46"
  },
  {
    "id": "GEOM_815",
    "topic": "Euclidean Geometry",
    "subtopic": "angle relationships",
    "difficulty": "hard",
    "question": "Two parallel lines are intersected by a transversal. A pair of co-interior angles are $(3x + 6)^\\circ$ and $(6x + 12)^\\circ$. Find the size of the larger angle.",
    "correct_answer": "120^\\circ",
    "wrong_answers_pool": [
      "129^\\circ",
      "102^\\circ",
      "-120^\\circ",
      "360^\\circ",
      "136^\\circ",
      "111^\\circ",
      "240^\\circ",
      "117^\\circ"
    ],
    "explanation": "Co-interior angles between parallel lines are supplementary. $3x + 6 + 6x + 12 = 180 \\implies 9x = 162 \\implies x = 18$. The angles are $60^\\circ$ and $120^\\circ$, so the larger is $120^\\circ$.",
    "exam_id": "EXAM_2026-W20_grade12_mathematics_paper2_47"
  },
  {
    "id": "STAT_899",
    "topic": "Statistics and Regression",
    "subtopic": "standard deviation",
    "difficulty": "medium",
    "question": "For the dataset [12, 25, 23, 14, 27, 15, 11, 24, 10, 24], how many data points lie within one standard deviation of the mean?",
    "correct_answer": "5",
    "wrong_answers_pool": [
      "0",
      "1",
      "2",
      "3",
      "4",
      "6",
      "7",
      "8"
    ],
    "explanation": "Mean = $18.50$, Std Dev = $6.31$. The interval is $(12.19; 24.81)$. There are $5$ values in this interval.",
    "exam_id": "EXAM_2026-W20_grade12_mathematics_paper2_48"
  },
  {
    "id": "ANAGEO_291",
    "topic": "Analytical Geometry",
    "subtopic": "distance formula",
    "difficulty": "hard",
    "question": "The distance between A$(6; -8)$ and B$(x; -8)$ is $\\sqrt{36}$. Find the possible value(s) of $x$.",
    "correct_answer": "0, 12",
    "wrong_answers_pool": [
      "0, 15",
      "-7, 0",
      "-5, 1",
      "-14, -4",
      "5, 12",
      "-9, 7",
      "0, 10",
      "5, 9"
    ],
    "explanation": "$\\sqrt{(x - 6)^2 + (-8 - -8)^2} = \\sqrt{36} \\implies (x - 6)^2 + 0 = 36 \\implies (x - 6)^2 = 36 \\implies x - 6 = \\pm 6 \\implies x = 12$ or $x = 0$.",
    "exam_id": "EXAM_2026-W20_grade12_mathematics_paper2_49"
  },
  {
    "id": "TRIG_140",
    "topic": "Trigonometry",
    "subtopic": "sine rule",
    "difficulty": "hard",
    "question": "In $\\Delta ABC$, $a = 12$, $b = 13$, and $\\angle C = 99^\\circ$. Calculate the area of the triangle (to 2 decimal places).",
    "correct_answer": "77.04",
    "wrong_answers_pool": [
      "38.52",
      "76.04",
      "0.01",
      "78.04",
      "77.96",
      "77.30",
      "115.56",
      "-77.04"
    ],
    "explanation": "$\\text{Area} = \\frac{1}{2}ab\\sin C = 0.5(12)(13)\\sin(99^\\circ) \\approx 77.04$.",
    "exam_id": "EXAM_2026-W20_grade12_mathematics_paper2_50"
  }
]