[
  {
    "id": "ALG_104",
    "topic": "Patterns, Functions and Algebra",
    "subtopic": "Linear equations",
    "difficulty": "medium",
    "question": "Solve for x: $3x + 5 = 8$",
    "correct_answer": "x = 1",
    "wrong_answers_pool": [
      "x = 0",
      "x = 2",
      "x = 3",
      "x = 4",
      "x = 11",
      "x = 14",
      "x = -15",
      "x = 17"
    ],
    "explanation": "Subtract $5$ from both sides, then divide by $3$ to get $x = 1$.",
    "exam_id": "EXAM_2026-W14_grade9_mathematics_1"
  },
  {
    "id": "NUM_752",
    "topic": "Numbers, Operations and Relationships",
    "subtopic": "Integers",
    "difficulty": "medium",
    "question": "Calculate: $-11 \\times -15$",
    "correct_answer": "165",
    "wrong_answers_pool": [
      "163",
      "164",
      "166",
      "167",
      "330",
      "174",
      "495",
      "175"
    ],
    "explanation": "The product of two negative numbers is positive: $-11 \\times -15 = 165$.",
    "exam_id": "EXAM_2026-W14_grade9_mathematics_2"
  },
  {
    "id": "GEO_123",
    "topic": "Space and Shape (Geometry)",
    "subtopic": "Triangles and quadrilaterals",
    "difficulty": "hard",
    "question": "An isosceles triangle has a vertex angle of $100^\\circ$. What is the size of each base angle?",
    "correct_answer": "40^\\circ",
    "wrong_answers_pool": [
      "34^\\circ",
      "37^\\circ",
      "38^\\circ",
      "39^\\circ",
      "41^\\circ",
      "42^\\circ",
      "44^\\circ",
      "45^\\circ"
    ],
    "explanation": "Base angles of an isosceles triangle are equal. Sum is $180^\\circ$. Base angle $= (180^\\circ - 100^\\circ) \\div 2 = 40^\\circ$.",
    "exam_id": "EXAM_2026-W14_grade9_mathematics_3"
  },
  {
    "id": "GEO_584",
    "topic": "Space and Shape (Geometry)",
    "subtopic": "Triangles and quadrilaterals",
    "difficulty": "medium",
    "question": "In a triangle, two interior opposite angles are $80^\\circ$ and $42^\\circ$. Calculate the size of the exterior angle.",
    "correct_answer": "122^\\circ",
    "wrong_answers_pool": [
      "132^\\circ",
      "-122^\\circ",
      "103^\\circ",
      "104^\\circ",
      "366^\\circ",
      "142^\\circ",
      "115^\\circ",
      "244^\\circ"
    ],
    "explanation": "The exterior angle of a triangle is equal to the sum of the two interior opposite angles. $80^\\circ + 42^\\circ = 122^\\circ$.",
    "exam_id": "EXAM_2026-W14_grade9_mathematics_4"
  },
  {
    "id": "NUM_060",
    "topic": "Numbers, Operations and Relationships",
    "subtopic": "Whole numbers",
    "difficulty": "hard",
    "question": "Calculate the quotient and remainder: $7051 \\div 30$",
    "correct_answer": "235 remainder 1",
    "wrong_answers_pool": [
      "236 remainder 1",
      "234 remainder 1",
      "235 remainder 2",
      "235 remainder 0",
      "237 remainder 1",
      "233 remainder 1",
      "240 remainder 19"
    ],
    "explanation": "$7051 \\div 30 = 235$ with a remainder of $1$.",
    "exam_id": "EXAM_2026-W14_grade9_mathematics_5"
  },
  {
    "id": "NUM_852",
    "topic": "Numbers, Operations and Relationships",
    "subtopic": "Ratio and proportion",
    "difficulty": "hard",
    "question": "If $x$ and $y$ are directly proportional, and $y = 8$ when $x = 4$, find $y$ when $x = 15$.",
    "correct_answer": "30",
    "wrong_answers_pool": [
      "32",
      "-30",
      "41",
      "10",
      "12",
      "28",
      "15",
      "47"
    ],
    "explanation": "Since $y = kx$, $k = \\frac{8}{4} = 2.0$. Then $y = 2.0 \\times 15 = 30$.",
    "exam_id": "EXAM_2026-W14_grade9_mathematics_6"
  },
  {
    "id": "MEAS_673",
    "topic": "Measurement",
    "subtopic": "Surface area and volume",
    "difficulty": "medium",
    "question": "Calculate the surface area of a rectangular prism with length $9$ cm, width $6$ cm, and height $5$ cm.",
    "correct_answer": "258 cm$^2$",
    "wrong_answers_pool": [
      "256 cm$^2$",
      "257 cm$^2$",
      "129 cm$^2$",
      "259 cm$^2$",
      "516 cm$^2$",
      "260 cm$^2$",
      "774 cm$^2$",
      "264 cm$^2$"
    ],
    "explanation": "Surface Area $= 2(lw + lh + wh) = 2(54 + 45 + 30) = 258$ cm$^2$.",
    "exam_id": "EXAM_2026-W14_grade9_mathematics_7"
  },
  {
    "id": "MEAS_213",
    "topic": "Measurement",
    "subtopic": "Unit conversions",
    "difficulty": "hard",
    "question": "Convert $34500$ cm$^2$ to m$^2$.",
    "correct_answer": "3.45 m$^2$",
    "wrong_answers_pool": [
      "0.290 m$^2$",
      "1.725 m$^2$",
      "2.450 m$^2$",
      "2.552 m$^2$",
      "4.450 m$^2$",
      "5.175 m$^2$",
      "6.900 m$^2$",
      "7.394 m$^2$"
    ],
    "explanation": "Since $1$ m $= 100$ cm, $1$ m$^2 = 100 \\times 100 = 10,000$ cm$^2$. Divide by $10,000$: $34500 \\div 10000 = 3.45$ m$^2$.",
    "exam_id": "EXAM_2026-W14_grade9_mathematics_8"
  },
  {
    "id": "NUM_800",
    "topic": "Numbers, Operations and Relationships",
    "subtopic": "Ratio and proportion",
    "difficulty": "medium",
    "question": "Divide $400$ in the ratio $5:5$. What is the smaller part?",
    "correct_answer": "$200$",
    "wrong_answers_pool": [
      "100",
      "196",
      "198",
      "199",
      "201",
      "202",
      "600",
      "203"
    ],
    "explanation": "Total parts = $5 + 5 = 10$. One part = $400 \\div 10 = 40$. Smaller part = $5 \\times 40 = 200$.",
    "exam_id": "EXAM_2026-W14_grade9_mathematics_9"
  },
  {
    "id": "ALG_016",
    "topic": "Patterns, Functions and Algebra",
    "subtopic": "Factorisation",
    "difficulty": "medium",
    "question": "Factorise the difference of two squares: $x^2 - 4$",
    "correct_answer": "$(x - 2)(x + 2)$",
    "wrong_answers_pool": [
      "(x - 2)(x - 2)",
      "(x + 2)(x + 2)",
      "(x - 4)(x + 1)",
      "(x - 3)(x + 1)",
      "(x - 2)(x + 3)",
      "(x - 3)(x + 2)",
      "(x - 4)(x + 4)"
    ],
    "explanation": "Use the rule $a^2 - b^2 = (a - b)(a + b)$. Here $a = x$ and $b = 2$.",
    "exam_id": "EXAM_2026-W14_grade9_mathematics_10"
  },
  {
    "id": "DATA_535",
    "topic": "Data Handling",
    "subtopic": "Mean, median, mode",
    "difficulty": "medium",
    "question": "Find the median of the data set: $2, 6, 8, 9, 12, 18$",
    "correct_answer": "8.5",
    "wrong_answers_pool": [
      "0.1",
      "4.2",
      "7.5",
      "9.5",
      "10.4",
      "12.8",
      "15.5",
      "17.0"
    ],
    "explanation": "The data is ordered. Since there is an even number of values, the median is the average of the two middle values: $\\frac{8 + 9}{2} = 8.5$.",
    "exam_id": "EXAM_2026-W14_grade9_mathematics_11"
  },
  {
    "id": "ALG_930",
    "topic": "Patterns, Functions and Algebra",
    "subtopic": "Numeric and geometric patterns",
    "difficulty": "medium",
    "question": "Determine the $19$th term of the sequence: $10, 15, 20, ...$",
    "correct_answer": "100",
    "wrong_answers_pool": [
      "98",
      "99",
      "101",
      "102",
      "200",
      "300",
      "108",
      "120"
    ],
    "explanation": "The general rule is $T_n = 5n + 5$. Therefore, $T_{19} = 5(19) + 5 = 100$.",
    "exam_id": "EXAM_2026-W14_grade9_mathematics_12"
  },
  {
    "id": "ALG_498",
    "topic": "Patterns, Functions and Algebra",
    "subtopic": "Linear equations",
    "difficulty": "medium",
    "question": "Solve for x: $6x + -9 = -21$",
    "correct_answer": "x = -2",
    "wrong_answers_pool": [
      "x = 0",
      "x = 2",
      "x = 6",
      "x = -22",
      "x = 14",
      "x = 16",
      "x = 17",
      "x = -14"
    ],
    "explanation": "Subtract $-9$ from both sides, then divide by $6$ to get $x = -2$.",
    "exam_id": "EXAM_2026-W14_grade9_mathematics_13"
  },
  {
    "id": "NUM_206",
    "topic": "Numbers, Operations and Relationships",
    "subtopic": "Integers",
    "difficulty": "hard",
    "question": "Calculate: $-9 - (-13) \\times (-1)$",
    "correct_answer": "-22",
    "wrong_answers_pool": [
      "-25",
      "-24",
      "-23",
      "-21",
      "-20",
      "-15",
      "-44",
      "-11"
    ],
    "explanation": "Follow BODMAS: first multiply $(-13) \\times (-1) = 13$, then subtract from $-9$: $-9 - (13) = -22$.",
    "exam_id": "EXAM_2026-W14_grade9_mathematics_14"
  },
  {
    "id": "DATA_873",
    "topic": "Data Handling",
    "subtopic": "Mean, median, mode",
    "difficulty": "hard",
    "question": "Determine the mode(s) of the data set: $27, 15, 27, 15, 27, 15$",
    "correct_answer": "Bimodal: 15 and 27",
    "wrong_answers_pool": [
      "Only 15",
      "Only 27",
      "21.0",
      "No mode",
      "42",
      "12"
    ],
    "explanation": "The mode is the most frequent value. Both $15$ and $27$ appear 3 times, so the data set is bimodal.",
    "exam_id": "EXAM_2026-W14_grade9_mathematics_15"
  },
  {
    "id": "ALG_475",
    "topic": "Patterns, Functions and Algebra",
    "subtopic": "Linear equations",
    "difficulty": "medium",
    "question": "Solve for x: $2x + -9 = -15$",
    "correct_answer": "x = -3",
    "wrong_answers_pool": [
      "x = 0",
      "x = 1",
      "x = 3",
      "x = 5",
      "x = -18",
      "x = -14",
      "x = -12",
      "x = -1"
    ],
    "explanation": "Subtract $-9$ from both sides, then divide by $2$ to get $x = -3$.",
    "exam_id": "EXAM_2026-W14_grade9_mathematics_16"
  },
  {
    "id": "MEAS_449",
    "topic": "Measurement",
    "subtopic": "Unit conversions",
    "difficulty": "medium",
    "question": "Convert $2501$ m$\\ell$ to liters.",
    "correct_answer": "2.501 $\\ell$",
    "wrong_answers_pool": [
      "0.400 $\\ell$",
      "1.501 $\\ell$",
      "1.250 $\\ell$",
      "3.752 $\\ell$",
      "3.501 $\\ell$",
      "5.002 $\\ell$",
      "4.017 $\\ell$",
      "12.302 $\\ell$"
    ],
    "explanation": "Divide by 1000: $2501 \\div 1000 = 2.501$ $\\ell$.",
    "exam_id": "EXAM_2026-W14_grade9_mathematics_17"
  },
  {
    "id": "ALG_478",
    "topic": "Patterns, Functions and Algebra",
    "subtopic": "Functions and graphs",
    "difficulty": "medium",
    "question": "Calculate the gradient of the line passing through $(-5; 5)$ and $(-4; 6)$.",
    "correct_answer": "1",
    "wrong_answers_pool": [
      "0",
      "2",
      "3",
      "4",
      "8",
      "9",
      "11",
      "-19"
    ],
    "explanation": "Gradient $m = \\frac{y_2 - y_1}{x_2 - x_1} = \\frac{6 - 5}{-4 - -5} = 1$.",
    "exam_id": "EXAM_2026-W14_grade9_mathematics_18"
  },
  {
    "id": "GEO_110",
    "topic": "Space and Shape (Geometry)",
    "subtopic": "Triangles and quadrilaterals",
    "difficulty": "hard",
    "question": "An isosceles triangle has a vertex angle of $50^\\circ$. What is the size of each base angle?",
    "correct_answer": "65^\\circ",
    "wrong_answers_pool": [
      "64^\\circ",
      "32^\\circ",
      "66^\\circ",
      "130^\\circ",
      "67^\\circ",
      "195^\\circ",
      "68^\\circ",
      "70^\\circ"
    ],
    "explanation": "Base angles of an isosceles triangle are equal. Sum is $180^\\circ$. Base angle $= (180^\\circ - 50^\\circ) \\div 2 = 65^\\circ$.",
    "exam_id": "EXAM_2026-W14_grade9_mathematics_19"
  },
  {
    "id": "NUM_775",
    "topic": "Numbers, Operations and Relationships",
    "subtopic": "Whole numbers",
    "difficulty": "hard",
    "question": "Calculate the quotient and remainder: $8404 \\div 42$",
    "correct_answer": "200 remainder 4",
    "wrong_answers_pool": [
      "201 remainder 4",
      "199 remainder 4",
      "200 remainder 5",
      "200 remainder 3",
      "202 remainder 4",
      "198 remainder 4",
      "204 remainder 6"
    ],
    "explanation": "$8404 \\div 42 = 200$ with a remainder of $4$.",
    "exam_id": "EXAM_2026-W14_grade9_mathematics_20"
  },
  {
    "id": "GEO_126",
    "topic": "Space and Shape (Geometry)",
    "subtopic": "Geometry of straight lines",
    "difficulty": "hard",
    "question": "Two vertically opposite angles are $(4x + 19)^\\circ$ and $(3x + 30)^\\circ$. Find the size of the angles.",
    "correct_answer": "63^\\circ",
    "wrong_answers_pool": [
      "64^\\circ",
      "-63^\\circ",
      "65^\\circ",
      "69^\\circ",
      "78^\\circ",
      "79^\\circ",
      "49^\\circ",
      "54^\\circ"
    ],
    "explanation": "Vertically opposite angles are equal. $4x + 19 = 3x + 30$. $1x = 11$. $x = 11$. The angle is $4(11) + 19 = 63^\\circ$.",
    "exam_id": "EXAM_2026-W14_grade9_mathematics_21"
  },
  {
    "id": "DATA_890",
    "topic": "Data Handling",
    "subtopic": "Mean, median, mode",
    "difficulty": "medium",
    "question": "Find the median of the data set: $7, 7, 15, 16, 17, 17$",
    "correct_answer": "15.5",
    "wrong_answers_pool": [
      "0.1",
      "-0.5",
      "32.3",
      "34.9",
      "4.4",
      "7.8",
      "14.5",
      "16.5"
    ],
    "explanation": "The data is ordered. Since there is an even number of values, the median is the average of the two middle values: $\\frac{15 + 16}{2} = 15.5$.",
    "exam_id": "EXAM_2026-W14_grade9_mathematics_22"
  },
  {
    "id": "DATA_900",
    "topic": "Data Handling",
    "subtopic": "Mean, median, mode",
    "difficulty": "hard",
    "question": "Determine the mode(s) of the data set: $28, 28, 20, 20, 20, 28$",
    "correct_answer": "Bimodal: 20 and 28",
    "wrong_answers_pool": [
      "Only 20",
      "Only 28",
      "24.0",
      "No mode",
      "48",
      "8"
    ],
    "explanation": "The mode is the most frequent value. Both $20$ and $28$ appear 3 times, so the data set is bimodal.",
    "exam_id": "EXAM_2026-W14_grade9_mathematics_23"
  },
  {
    "id": "ALG_013",
    "topic": "Patterns, Functions and Algebra",
    "subtopic": "Numeric and geometric patterns",
    "difficulty": "hard",
    "question": "Find the next term in the geometric sequence: $4, 16, 64, 256, ...$",
    "correct_answer": "1024",
    "wrong_answers_pool": [
      "-1024",
      "1025",
      "512",
      "2048",
      "1026",
      "3072",
      "1030",
      "1031"
    ],
    "explanation": "The constant ratio is $4$. Therefore, $256 \\times 4 = 1024$.",
    "exam_id": "EXAM_2026-W14_grade9_mathematics_24"
  },
  {
    "id": "DATA_054",
    "topic": "Data Handling",
    "subtopic": "Mean, median, mode",
    "difficulty": "hard",
    "question": "Determine the mode(s) of the data set: $29, 12, 12, 29, 29, 12$",
    "correct_answer": "Bimodal: 12 and 29",
    "wrong_answers_pool": [
      "Only 12",
      "Only 29",
      "20.5",
      "No mode",
      "41",
      "17"
    ],
    "explanation": "The mode is the most frequent value. Both $12$ and $29$ appear 3 times, so the data set is bimodal.",
    "exam_id": "EXAM_2026-W14_grade9_mathematics_25"
  },
  {
    "id": "NUM_688",
    "topic": "Numbers, Operations and Relationships",
    "subtopic": "Fractions and decimals",
    "difficulty": "medium",
    "question": "Calculate: $7.65 \\times 7.47$",
    "correct_answer": "57.1455",
    "wrong_answers_pool": [
      "0.0175",
      "64.6378",
      "-57.1455",
      "39.3164",
      "45.6838",
      "77.0655",
      "45.7460",
      "114.2910"
    ],
    "explanation": "$7.65 \\times 7.47 = 57.1455$.",
    "exam_id": "EXAM_2026-W14_grade9_mathematics_26"
  },
  {
    "id": "GEO_413",
    "topic": "Space and Shape (Geometry)",
    "subtopic": "Geometry of straight lines",
    "difficulty": "hard",
    "question": "Two vertically opposite angles are $(4x + 14)^\\circ$ and $(2x + 18)^\\circ$. Find the size of the angles.",
    "correct_answer": "22^\\circ",
    "wrong_answers_pool": [
      "33^\\circ",
      "66^\\circ",
      "3^\\circ",
      "41^\\circ",
      "-22^\\circ",
      "11^\\circ",
      "44^\\circ",
      "18^\\circ"
    ],
    "explanation": "Vertically opposite angles are equal. $4x + 14 = 2x + 18$. $2x = 4$. $x = 2$. The angle is $4(2) + 14 = 22^\\circ$.",
    "exam_id": "EXAM_2026-W14_grade9_mathematics_27"
  },
  {
    "id": "GEO_050",
    "topic": "Space and Shape (Geometry)",
    "subtopic": "Triangles and quadrilaterals",
    "difficulty": "hard",
    "question": "An isosceles triangle has a vertex angle of $116^\\circ$. What is the size of each base angle?",
    "correct_answer": "32^\\circ",
    "wrong_answers_pool": [
      "-32^\\circ",
      "33^\\circ",
      "64^\\circ",
      "34^\\circ",
      "96^\\circ",
      "36^\\circ",
      "41^\\circ",
      "42^\\circ"
    ],
    "explanation": "Base angles of an isosceles triangle are equal. Sum is $180^\\circ$. Base angle $= (180^\\circ - 116^\\circ) \\div 2 = 32^\\circ$.",
    "exam_id": "EXAM_2026-W14_grade9_mathematics_28"
  },
  {
    "id": "MEAS_818",
    "topic": "Measurement",
    "subtopic": "Surface area and volume",
    "difficulty": "hard",
    "question": "Calculate the volume of a cylinder with radius $7$ cm and height $11$ cm. Use $\\pi \\approx 3.14$.",
    "correct_answer": "1692.46 cm$^3$",
    "wrong_answers_pool": [
      "0.00 cm$^3$",
      "1698.99 cm$^3$",
      "-1692.46 cm$^3$",
      "2538.69 cm$^3$",
      "1708.35 cm$^3$",
      "846.23 cm$^3$",
      "1691.39 cm$^3$",
      "1683.16 cm$^3$"
    ],
    "explanation": "Volume $= \\pi r^2 h \\approx 3.14 \\times (7)^2 \\times 11 = 1692.46$ cm$^3$.",
    "exam_id": "EXAM_2026-W14_grade9_mathematics_29"
  },
  {
    "id": "ALG_348",
    "topic": "Patterns, Functions and Algebra",
    "subtopic": "Algebraic expressions",
    "difficulty": "medium",
    "question": "Expand: $5(4x + 4)$",
    "correct_answer": "$20x + 20$",
    "wrong_answers_pool": [
      "20x + 4",
      "4x + 20",
      "9x + 9",
      "20x - 20",
      "20x + 21",
      "21x + 20",
      "20x^2 + 20"
    ],
    "explanation": "Multiply each term inside the bracket by $5$: $5 \\times 4x + 5 \\times 4 = 20x + 20$.",
    "exam_id": "EXAM_2026-W14_grade9_mathematics_30"
  },
  {
    "id": "MEAS_730",
    "topic": "Measurement",
    "subtopic": "Surface area and volume",
    "difficulty": "hard",
    "question": "Calculate the volume of a cylinder with radius $5$ cm and height $6$ cm. Use $\\pi \\approx 3.14$.",
    "correct_answer": "471.0 cm$^3$",
    "wrong_answers_pool": [
      "0.00 cm$^3$",
      "706.50 cm$^3$",
      "487.33 cm$^3$",
      "-471.00 cm$^3$",
      "235.50 cm$^3$",
      "459.82 cm$^3$",
      "461.83 cm$^3$",
      "942.00 cm$^3$"
    ],
    "explanation": "Volume $= \\pi r^2 h \\approx 3.14 \\times (5)^2 \\times 6 = 471.0$ cm$^3$.",
    "exam_id": "EXAM_2026-W14_grade9_mathematics_31"
  },
  {
    "id": "ALG_235",
    "topic": "Patterns, Functions and Algebra",
    "subtopic": "Algebraic expressions",
    "difficulty": "medium",
    "question": "Expand: $4(5x + 4)$",
    "correct_answer": "$20x + 16$",
    "wrong_answers_pool": [
      "20x + 4",
      "5x + 16",
      "9x + 8",
      "20x - 16",
      "20x + 17",
      "21x + 16",
      "20x^2 + 16"
    ],
    "explanation": "Multiply each term inside the bracket by $4$: $4 \\times 5x + 4 \\times 4 = 20x + 16$.",
    "exam_id": "EXAM_2026-W14_grade9_mathematics_32"
  },
  {
    "id": "GEO_166",
    "topic": "Space and Shape (Geometry)",
    "subtopic": "Triangles and quadrilaterals",
    "difficulty": "medium",
    "question": "In a triangle, two interior opposite angles are $80^\\circ$ and $63^\\circ$. Calculate the size of the exterior angle.",
    "correct_answer": "143^\\circ",
    "wrong_answers_pool": [
      "128^\\circ",
      "71^\\circ",
      "137^\\circ",
      "141^\\circ",
      "142^\\circ",
      "429^\\circ",
      "144^\\circ",
      "-143^\\circ"
    ],
    "explanation": "The exterior angle of a triangle is equal to the sum of the two interior opposite angles. $80^\\circ + 63^\\circ = 143^\\circ$.",
    "exam_id": "EXAM_2026-W14_grade9_mathematics_33"
  },
  {
    "id": "GEO_211",
    "topic": "Space and Shape (Geometry)",
    "subtopic": "Transformations",
    "difficulty": "medium",
    "question": "Point $A(2; 4)$ is reflected across the x-axis. What are the coordinates of $A'$?",
    "correct_answer": "(2; -4)",
    "wrong_answers_pool": [
      "(-2; 4)",
      "(-2; -4)",
      "(4; 2)",
      "(-4; -2)",
      "(4; -2)",
      "(-4; 2)",
      "(2; 4)"
    ],
    "explanation": "Reflection across the x-axis changes the sign of the y-coordinate: $(x; y) \\rightarrow (x; -y)$. Thus $(2; -4)$.",
    "exam_id": "EXAM_2026-W14_grade9_mathematics_34"
  },
  {
    "id": "ALG_966",
    "topic": "Patterns, Functions and Algebra",
    "subtopic": "Numeric and geometric patterns",
    "difficulty": "medium",
    "question": "Determine the $18$th term of the sequence: $6, 11, 16, ...$",
    "correct_answer": "91",
    "wrong_answers_pool": [
      "-91",
      "71",
      "45",
      "109",
      "273",
      "182",
      "87",
      "86"
    ],
    "explanation": "The general rule is $T_n = 5n + 1$. Therefore, $T_{18} = 5(18) + 1 = 91$.",
    "exam_id": "EXAM_2026-W14_grade9_mathematics_35"
  },
  {
    "id": "GEO_259",
    "topic": "Space and Shape (Geometry)",
    "subtopic": "Pythagoras",
    "difficulty": "hard",
    "question": "In a right-angled triangle, the two shorter sides are $7$ cm and $7$ cm. Calculate the length of the hypotenuse correct to 2 decimal places.",
    "correct_answer": "9.9 cm",
    "wrong_answers_pool": [
      "0.10 cm",
      "4.95 cm",
      "6.58 cm",
      "8.90 cm",
      "9.43 cm",
      "10.90 cm",
      "14.85 cm",
      "19.80 cm"
    ],
    "explanation": "Using Pythagoras: $c^2 = 7^2 + 7^2 = 49 + 49 = 98$. $c = \\sqrt{98} \\approx 9.9$ cm.",
    "exam_id": "EXAM_2026-W14_grade9_mathematics_36"
  },
  {
    "id": "GEO_771",
    "topic": "Space and Shape (Geometry)",
    "subtopic": "Transformations",
    "difficulty": "hard",
    "question": "Point $B(1; 3)$ is enlarged by a scale factor of $4$ through the origin. What are the new coordinates?",
    "correct_answer": "(4; 12)",
    "wrong_answers_pool": [
      "(5; 7)",
      "(4; 3)",
      "(1; 12)",
      "(0.2; 0.8)",
      "(12; 4)",
      "(-4; -12)",
      "(5; 13)"
    ],
    "explanation": "Multiply both coordinates by the scale factor $4$: $(1 \\times 4; 3 \\times 4) = (4; 12)$.",
    "exam_id": "EXAM_2026-W14_grade9_mathematics_37"
  },
  {
    "id": "NUM_061",
    "topic": "Numbers, Operations and Relationships",
    "subtopic": "Integers",
    "difficulty": "medium",
    "question": "Calculate: $-18 \\times -3$",
    "correct_answer": "54",
    "wrong_answers_pool": [
      "162",
      "34",
      "36",
      "40",
      "41",
      "-54",
      "108",
      "44"
    ],
    "explanation": "The product of two negative numbers is positive: $-18 \\times -3 = 54$.",
    "exam_id": "EXAM_2026-W14_grade9_mathematics_38"
  },
  {
    "id": "NUM_068",
    "topic": "Numbers, Operations and Relationships",
    "subtopic": "Percentages and financial maths",
    "difficulty": "hard",
    "question": "Calculate the final amount if R$8566$ is invested at $5\\%$ p.a. compound interest for $3$ years. (Round to 2 decimal places)",
    "correct_answer": "R$9916.22$",
    "wrong_answers_pool": [
      "R$0.00",
      "R$9921.99",
      "R$-9916.22",
      "R$9915.69",
      "R$9897.34",
      "R$9899.78",
      "R$9900.51",
      "R$19832.44"
    ],
    "explanation": "$A = P(1 + i)^n = 8566(1 + 0.05)^3 = 9916.22$.",
    "exam_id": "EXAM_2026-W14_grade9_mathematics_39"
  },
  {
    "id": "NUM_266",
    "topic": "Numbers, Operations and Relationships",
    "subtopic": "Percentages and financial maths",
    "difficulty": "hard",
    "question": "Calculate the final amount if R$9508$ is invested at $12\\%$ p.a. compound interest for $3$ years. (Round to 2 decimal places)",
    "correct_answer": "R$13358.06$",
    "wrong_answers_pool": [
      "R$0.00",
      "R$13344.88",
      "R$20037.09",
      "R$13357.06",
      "R$13359.06",
      "R$13360.24",
      "R$-13358.06",
      "R$13365.55"
    ],
    "explanation": "$A = P(1 + i)^n = 9508(1 + 0.12)^3 = 13358.06$.",
    "exam_id": "EXAM_2026-W14_grade9_mathematics_40"
  },
  {
    "id": "ALG_807",
    "topic": "Patterns, Functions and Algebra",
    "subtopic": "Linear equations",
    "difficulty": "medium",
    "question": "Solve for x: $5x + 1 = -4$",
    "correct_answer": "x = -1",
    "wrong_answers_pool": [
      "x = 0",
      "x = 1",
      "x = 4",
      "x = 7",
      "x = 8",
      "x = -18",
      "x = 17",
      "x = -14"
    ],
    "explanation": "Subtract $1$ from both sides, then divide by $5$ to get $x = -1$.",
    "exam_id": "EXAM_2026-W14_grade9_mathematics_41"
  },
  {
    "id": "ALG_217",
    "topic": "Patterns, Functions and Algebra",
    "subtopic": "Numeric and geometric patterns",
    "difficulty": "medium",
    "question": "Determine the $10$th term of the sequence: $7, 10, 13, ...$",
    "correct_answer": "34",
    "wrong_answers_pool": [
      "32",
      "33",
      "35",
      "68",
      "36",
      "102",
      "40",
      "17"
    ],
    "explanation": "The general rule is $T_n = 3n + 4$. Therefore, $T_{10} = 3(10) + 4 = 34$.",
    "exam_id": "EXAM_2026-W14_grade9_mathematics_42"
  },
  {
    "id": "GEO_808",
    "topic": "Space and Shape (Geometry)",
    "subtopic": "Pythagoras",
    "difficulty": "hard",
    "question": "In a right-angled triangle, the two shorter sides are $6$ cm and $10$ cm. Calculate the length of the hypotenuse correct to 2 decimal places.",
    "correct_answer": "11.66 cm",
    "wrong_answers_pool": [
      "0.09 cm",
      "5.83 cm",
      "6.96 cm",
      "10.66 cm",
      "12.66 cm",
      "17.49 cm",
      "19.51 cm",
      "23.15 cm"
    ],
    "explanation": "Using Pythagoras: $c^2 = 6^2 + 10^2 = 36 + 100 = 136$. $c = \\sqrt{136} \\approx 11.66$ cm.",
    "exam_id": "EXAM_2026-W14_grade9_mathematics_43"
  },
  {
    "id": "ALG_779",
    "topic": "Patterns, Functions and Algebra",
    "subtopic": "Linear equations",
    "difficulty": "hard",
    "question": "Solve for x: $2(x + -4) = 5x + -2$",
    "correct_answer": "x = -2",
    "wrong_answers_pool": [
      "x = 0",
      "x = 2",
      "x = 5",
      "x = 6",
      "x = -22",
      "x = -21",
      "x = -20",
      "x = 17"
    ],
    "explanation": "Expand: $2x + -8 = 5x + -2$. Group x terms: $-3x = 6$. Therefore $x = -2$.",
    "exam_id": "EXAM_2026-W14_grade9_mathematics_44"
  },
  {
    "id": "ALG_695",
    "topic": "Patterns, Functions and Algebra",
    "subtopic": "Functions and graphs",
    "difficulty": "hard",
    "question": "Find the equation of the line with gradient $1$ passing through the point $(-1; -5)$.",
    "correct_answer": "$y = 1x - 4$",
    "wrong_answers_pool": [
      "$y = 1x - 3$",
      "$y = 1x - 5$",
      "$y = -1x - 4$",
      "$y = 1x + 4$",
      "$y = -4x + 1$",
      "$y = -1x - 5$",
      "$y = 1x - 2$"
    ],
    "explanation": "Use $y = mx + c$. Substitute $m=1, x=-1, y=-5$: $-5 = 1(-1) + c$. Solving for $c$ gives $c = -4$.",
    "exam_id": "EXAM_2026-W14_grade9_mathematics_45"
  },
  {
    "id": "DATA_626",
    "topic": "Data Handling",
    "subtopic": "Mean, median, mode",
    "difficulty": "hard",
    "question": "Determine the mode(s) of the data set: $15, 29, 29, 15, 29, 15$",
    "correct_answer": "Bimodal: 15 and 29",
    "wrong_answers_pool": [
      "Only 15",
      "Only 29",
      "22.0",
      "No mode",
      "44",
      "14"
    ],
    "explanation": "The mode is the most frequent value. Both $15$ and $29$ appear 3 times, so the data set is bimodal.",
    "exam_id": "EXAM_2026-W14_grade9_mathematics_46"
  },
  {
    "id": "NUM_574",
    "topic": "Numbers, Operations and Relationships",
    "subtopic": "Ratio and proportion",
    "difficulty": "hard",
    "question": "If $x$ and $y$ are directly proportional, and $y = 6$ when $x = 2$, find $y$ when $x = 25$.",
    "correct_answer": "75",
    "wrong_answers_pool": [
      "225",
      "68",
      "37",
      "70",
      "73",
      "74",
      "76",
      "77"
    ],
    "explanation": "Since $y = kx$, $k = \\frac{6}{2} = 3.0$. Then $y = 3.0 \\times 25 = 75$.",
    "exam_id": "EXAM_2026-W14_grade9_mathematics_47"
  },
  {
    "id": "ALG_220",
    "topic": "Patterns, Functions and Algebra",
    "subtopic": "Algebraic expressions",
    "difficulty": "medium",
    "question": "Expand: $5(3x + 2)$",
    "correct_answer": "$15x + 10$",
    "wrong_answers_pool": [
      "15x + 2",
      "3x + 10",
      "8x + 7",
      "15x - 10",
      "15x + 11",
      "16x + 10",
      "15x^2 + 10"
    ],
    "explanation": "Multiply each term inside the bracket by $5$: $5 \\times 3x + 5 \\times 2 = 15x + 10$.",
    "exam_id": "EXAM_2026-W14_grade9_mathematics_48"
  },
  {
    "id": "DATA_785",
    "topic": "Data Handling",
    "subtopic": "Mean, median, mode",
    "difficulty": "medium",
    "question": "Find the median of the data set: $2, 3, 4, 13, 15, 16$",
    "correct_answer": "8.5",
    "wrong_answers_pool": [
      "0.1",
      "4.2",
      "7.5",
      "9.5",
      "12.8",
      "15.1",
      "17.0",
      "20.6"
    ],
    "explanation": "The data is ordered. Since there is an even number of values, the median is the average of the two middle values: $\\frac{4 + 13}{2} = 8.5$.",
    "exam_id": "EXAM_2026-W14_grade9_mathematics_49"
  },
  {
    "id": "GEO_832",
    "topic": "Space and Shape (Geometry)",
    "subtopic": "Triangles and quadrilaterals",
    "difficulty": "medium",
    "question": "In a triangle, two interior opposite angles are $49^\\circ$ and $46^\\circ$. Calculate the size of the exterior angle.",
    "correct_answer": "95^\\circ",
    "wrong_answers_pool": [
      "96^\\circ",
      "-95^\\circ",
      "97^\\circ",
      "109^\\circ",
      "78^\\circ",
      "47^\\circ",
      "112^\\circ",
      "114^\\circ"
    ],
    "explanation": "The exterior angle of a triangle is equal to the sum of the two interior opposite angles. $49^\\circ + 46^\\circ = 95^\\circ$.",
    "exam_id": "EXAM_2026-W14_grade9_mathematics_50"
  }
]